<?xml version="1.0" encoding="utf-8"?>
<NetworkData xmlns:xsd="http://www.w3.org/2001/XMLSchema" xmlns:xsi="http://www.w3.org/2001/XMLSchema-instance">
  <Layers>
    <LayerData>
      <ActType>RAMP</ActType>
      <NumNeuron>18</NumNeuron>
      <Bias>
        <double>0</double>
        <double>0</double>
        <double>0</double>
        <double>0</double>
        <double>0</double>
        <double>0</double>
        <double>0</double>
        <double>0</double>
        <double>0</double>
        <double>0</double>
        <double>0</double>
        <double>0</double>
        <double>0</double>
        <double>0</double>
        <double>0</double>
        <double>0</double>
        <double>0</double>
        <double>0</double>
      </Bias>
    </LayerData>
    <LayerData>
      <ActType>SIGMOID</ActType>
      <NumNeuron>18</NumNeuron>
      <Bias>
        <double>0</double>
        <double>0</double>
        <double>0</double>
        <double>0</double>
        <double>0</double>
        <double>0</double>
        <double>0</double>
        <double>0</double>
        <double>0</double>
        <double>0</double>
        <double>0</double>
        <double>0</double>
        <double>0</double>
        <double>0</double>
        <double>0</double>
        <double>0</double>
        <double>0</double>
        <double>0</double>
      </Bias>
    </LayerData>
    <LayerData>
      <ActType>SIGMOID</ActType>
      <NumNeuron>4</NumNeuron>
      <Bias>
        <double>0</double>
        <double>0</double>
        <double>0</double>
        <double>0</double>
      </Bias>
    </LayerData>
  </Layers>
  <Connections>
    <ConnectionData>
      <From>
        <Layer>0</Layer>
        <Node>0</Node>
      </From>
      <To>
        <Layer>1</Layer>
        <Node>0</Node>
      </To>
      <Weight>0.15654606542389193</Weight>
    </ConnectionData>
    <ConnectionData>
      <From>
        <Layer>0</Layer>
        <Node>0</Node>
      </From>
      <To>
        <Layer>1</Layer>
        <Node>1</Node>
      </To>
      <Weight>0.34402413379588359</Weight>
    </ConnectionData>
    <ConnectionData>
      <From>
        <Layer>0</Layer>
        <Node>0</Node>
      </From>
      <To>
        <Layer>1</Layer>
        <Node>2</Node>
      </To>
      <Weight>-0.036165615793394668</Weight>
    </ConnectionData>
    <ConnectionData>
      <From>
        <Layer>0</Layer>
        <Node>0</Node>
      </From>
      <To>
        <Layer>1</Layer>
        <Node>3</Node>
      </To>
      <Weight>0.38966906065571538</Weight>
    </ConnectionData>
    <ConnectionData>
      <From>
        <Layer>0</Layer>
        <Node>0</Node>
      </From>
      <To>
        <Layer>1</Layer>
        <Node>4</Node>
      </To>
      <Weight>-0.17126603269542851</Weight>
    </ConnectionData>
    <ConnectionData>
      <From>
        <Layer>0</Layer>
        <Node>0</Node>
      </From>
      <To>
        <Layer>1</Layer>
        <Node>5</Node>
      </To>
      <Weight>-0.398170543787149</Weight>
    </ConnectionData>
    <ConnectionData>
      <From>
        <Layer>0</Layer>
        <Node>0</Node>
      </From>
      <To>
        <Layer>1</Layer>
        <Node>6</Node>
      </To>
      <Weight>-0.23340091469390362</Weight>
    </ConnectionData>
    <ConnectionData>
      <From>
        <Layer>0</Layer>
        <Node>0</Node>
      </From>
      <To>
        <Layer>1</Layer>
        <Node>7</Node>
      </To>
      <Weight>-0.21764914212638936</Weight>
    </ConnectionData>
    <ConnectionData>
      <From>
        <Layer>0</Layer>
        <Node>0</Node>
      </From>
      <To>
        <Layer>1</Layer>
        <Node>8</Node>
      </To>
      <Weight>-0.18089538564947216</Weight>
    </ConnectionData>
    <ConnectionData>
      <From>
        <Layer>0</Layer>
        <Node>0</Node>
      </From>
      <To>
        <Layer>1</Layer>
        <Node>9</Node>
      </To>
      <Weight>0.29609757326361608</Weight>
    </ConnectionData>
    <ConnectionData>
      <From>
        <Layer>0</Layer>
        <Node>0</Node>
      </From>
      <To>
        <Layer>1</Layer>
        <Node>10</Node>
      </To>
      <Weight>0.22591590263224948</Weight>
    </ConnectionData>
    <ConnectionData>
      <From>
        <Layer>0</Layer>
        <Node>0</Node>
      </From>
      <To>
        <Layer>1</Layer>
        <Node>11</Node>
      </To>
      <Weight>0.45754538101961151</Weight>
    </ConnectionData>
    <ConnectionData>
      <From>
        <Layer>0</Layer>
        <Node>0</Node>
      </From>
      <To>
        <Layer>1</Layer>
        <Node>12</Node>
      </To>
      <Weight>-0.29526468589681421</Weight>
    </ConnectionData>
    <ConnectionData>
      <From>
        <Layer>0</Layer>
        <Node>0</Node>
      </From>
      <To>
        <Layer>1</Layer>
        <Node>13</Node>
      </To>
      <Weight>0.076785024989761919</Weight>
    </ConnectionData>
    <ConnectionData>
      <From>
        <Layer>0</Layer>
        <Node>0</Node>
      </From>
      <To>
        <Layer>1</Layer>
        <Node>14</Node>
      </To>
      <Weight>0.18742888359698884</Weight>
    </ConnectionData>
    <ConnectionData>
      <From>
        <Layer>0</Layer>
        <Node>0</Node>
      </From>
      <To>
        <Layer>1</Layer>
        <Node>15</Node>
      </To>
      <Weight>-0.45043289891929966</Weight>
    </ConnectionData>
    <ConnectionData>
      <From>
        <Layer>0</Layer>
        <Node>0</Node>
      </From>
      <To>
        <Layer>1</Layer>
        <Node>16</Node>
      </To>
      <Weight>0.42229689886900457</Weight>
    </ConnectionData>
    <ConnectionData>
      <From>
        <Layer>0</Layer>
        <Node>0</Node>
      </From>
      <To>
        <Layer>1</Layer>
        <Node>17</Node>
      </To>
      <Weight>0.17276600872760917</Weight>
    </ConnectionData>
    <ConnectionData>
      <From>
        <Layer>0</Layer>
        <Node>1</Node>
      </From>
      <To>
        <Layer>1</Layer>
        <Node>0</Node>
      </To>
      <Weight>-0.051407957240663438</Weight>
    </ConnectionData>
    <ConnectionData>
      <From>
        <Layer>0</Layer>
        <Node>1</Node>
      </From>
      <To>
        <Layer>1</Layer>
        <Node>1</Node>
      </To>
      <Weight>0.11496707127195183</Weight>
    </ConnectionData>
    <ConnectionData>
      <From>
        <Layer>0</Layer>
        <Node>1</Node>
      </From>
      <To>
        <Layer>1</Layer>
        <Node>2</Node>
      </To>
      <Weight>-0.34535420725371418</Weight>
    </ConnectionData>
    <ConnectionData>
      <From>
        <Layer>0</Layer>
        <Node>1</Node>
      </From>
      <To>
        <Layer>1</Layer>
        <Node>3</Node>
      </To>
      <Weight>-0.2556358523460272</Weight>
    </ConnectionData>
    <ConnectionData>
      <From>
        <Layer>0</Layer>
        <Node>1</Node>
      </From>
      <To>
        <Layer>1</Layer>
        <Node>4</Node>
      </To>
      <Weight>-0.21643555383963303</Weight>
    </ConnectionData>
    <ConnectionData>
      <From>
        <Layer>0</Layer>
        <Node>1</Node>
      </From>
      <To>
        <Layer>1</Layer>
        <Node>5</Node>
      </To>
      <Weight>0.2362409153656293</Weight>
    </ConnectionData>
    <ConnectionData>
      <From>
        <Layer>0</Layer>
        <Node>1</Node>
      </From>
      <To>
        <Layer>1</Layer>
        <Node>6</Node>
      </To>
      <Weight>0.35054471709325197</Weight>
    </ConnectionData>
    <ConnectionData>
      <From>
        <Layer>0</Layer>
        <Node>1</Node>
      </From>
      <To>
        <Layer>1</Layer>
        <Node>7</Node>
      </To>
      <Weight>0.17939837262006397</Weight>
    </ConnectionData>
    <ConnectionData>
      <From>
        <Layer>0</Layer>
        <Node>1</Node>
      </From>
      <To>
        <Layer>1</Layer>
        <Node>8</Node>
      </To>
      <Weight>-0.1150520972977635</Weight>
    </ConnectionData>
    <ConnectionData>
      <From>
        <Layer>0</Layer>
        <Node>1</Node>
      </From>
      <To>
        <Layer>1</Layer>
        <Node>9</Node>
      </To>
      <Weight>0.39719235380049434</Weight>
    </ConnectionData>
    <ConnectionData>
      <From>
        <Layer>0</Layer>
        <Node>1</Node>
      </From>
      <To>
        <Layer>1</Layer>
        <Node>10</Node>
      </To>
      <Weight>0.46635015167591631</Weight>
    </ConnectionData>
    <ConnectionData>
      <From>
        <Layer>0</Layer>
        <Node>1</Node>
      </From>
      <To>
        <Layer>1</Layer>
        <Node>11</Node>
      </To>
      <Weight>-0.068884453069830542</Weight>
    </ConnectionData>
    <ConnectionData>
      <From>
        <Layer>0</Layer>
        <Node>1</Node>
      </From>
      <To>
        <Layer>1</Layer>
        <Node>12</Node>
      </To>
      <Weight>-0.23276920976711868</Weight>
    </ConnectionData>
    <ConnectionData>
      <From>
        <Layer>0</Layer>
        <Node>1</Node>
      </From>
      <To>
        <Layer>1</Layer>
        <Node>13</Node>
      </To>
      <Weight>-0.18086972491856185</Weight>
    </ConnectionData>
    <ConnectionData>
      <From>
        <Layer>0</Layer>
        <Node>1</Node>
      </From>
      <To>
        <Layer>1</Layer>
        <Node>14</Node>
      </To>
      <Weight>-0.42173526991239529</Weight>
    </ConnectionData>
    <ConnectionData>
      <From>
        <Layer>0</Layer>
        <Node>1</Node>
      </From>
      <To>
        <Layer>1</Layer>
        <Node>15</Node>
      </To>
      <Weight>-0.26842668036391337</Weight>
    </ConnectionData>
    <ConnectionData>
      <From>
        <Layer>0</Layer>
        <Node>1</Node>
      </From>
      <To>
        <Layer>1</Layer>
        <Node>16</Node>
      </To>
      <Weight>0.027938766185165775</Weight>
    </ConnectionData>
    <ConnectionData>
      <From>
        <Layer>0</Layer>
        <Node>1</Node>
      </From>
      <To>
        <Layer>1</Layer>
        <Node>17</Node>
      </To>
      <Weight>0.27882246755940021</Weight>
    </ConnectionData>
    <ConnectionData>
      <From>
        <Layer>0</Layer>
        <Node>2</Node>
      </From>
      <To>
        <Layer>1</Layer>
        <Node>0</Node>
      </To>
      <Weight>0.23940242488840713</Weight>
    </ConnectionData>
    <ConnectionData>
      <From>
        <Layer>0</Layer>
        <Node>2</Node>
      </From>
      <To>
        <Layer>1</Layer>
        <Node>1</Node>
      </To>
      <Weight>-0.16843048234862762</Weight>
    </ConnectionData>
    <ConnectionData>
      <From>
        <Layer>0</Layer>
        <Node>2</Node>
      </From>
      <To>
        <Layer>1</Layer>
        <Node>2</Node>
      </To>
      <Weight>-0.13530350086991838</Weight>
    </ConnectionData>
    <ConnectionData>
      <From>
        <Layer>0</Layer>
        <Node>2</Node>
      </From>
      <To>
        <Layer>1</Layer>
        <Node>3</Node>
      </To>
      <Weight>0.086083432001100579</Weight>
    </ConnectionData>
    <ConnectionData>
      <From>
        <Layer>0</Layer>
        <Node>2</Node>
      </From>
      <To>
        <Layer>1</Layer>
        <Node>4</Node>
      </To>
      <Weight>0.40351075069210995</Weight>
    </ConnectionData>
    <ConnectionData>
      <From>
        <Layer>0</Layer>
        <Node>2</Node>
      </From>
      <To>
        <Layer>1</Layer>
        <Node>5</Node>
      </To>
      <Weight>-0.32561198753566112</Weight>
    </ConnectionData>
    <ConnectionData>
      <From>
        <Layer>0</Layer>
        <Node>2</Node>
      </From>
      <To>
        <Layer>1</Layer>
        <Node>6</Node>
      </To>
      <Weight>0.071477651396523068</Weight>
    </ConnectionData>
    <ConnectionData>
      <From>
        <Layer>0</Layer>
        <Node>2</Node>
      </From>
      <To>
        <Layer>1</Layer>
        <Node>7</Node>
      </To>
      <Weight>0.21897670287591253</Weight>
    </ConnectionData>
    <ConnectionData>
      <From>
        <Layer>0</Layer>
        <Node>2</Node>
      </From>
      <To>
        <Layer>1</Layer>
        <Node>8</Node>
      </To>
      <Weight>0.47064866170783004</Weight>
    </ConnectionData>
    <ConnectionData>
      <From>
        <Layer>0</Layer>
        <Node>2</Node>
      </From>
      <To>
        <Layer>1</Layer>
        <Node>9</Node>
      </To>
      <Weight>0.057687142192240359</Weight>
    </ConnectionData>
    <ConnectionData>
      <From>
        <Layer>0</Layer>
        <Node>2</Node>
      </From>
      <To>
        <Layer>1</Layer>
        <Node>10</Node>
      </To>
      <Weight>-0.42587783184176209</Weight>
    </ConnectionData>
    <ConnectionData>
      <From>
        <Layer>0</Layer>
        <Node>2</Node>
      </From>
      <To>
        <Layer>1</Layer>
        <Node>11</Node>
      </To>
      <Weight>0.39419611119394937</Weight>
    </ConnectionData>
    <ConnectionData>
      <From>
        <Layer>0</Layer>
        <Node>2</Node>
      </From>
      <To>
        <Layer>1</Layer>
        <Node>12</Node>
      </To>
      <Weight>-0.35078572707752964</Weight>
    </ConnectionData>
    <ConnectionData>
      <From>
        <Layer>0</Layer>
        <Node>2</Node>
      </From>
      <To>
        <Layer>1</Layer>
        <Node>13</Node>
      </To>
      <Weight>0.29332042103322242</Weight>
    </ConnectionData>
    <ConnectionData>
      <From>
        <Layer>0</Layer>
        <Node>2</Node>
      </From>
      <To>
        <Layer>1</Layer>
        <Node>14</Node>
      </To>
      <Weight>0.20141923413678031</Weight>
    </ConnectionData>
    <ConnectionData>
      <From>
        <Layer>0</Layer>
        <Node>2</Node>
      </From>
      <To>
        <Layer>1</Layer>
        <Node>15</Node>
      </To>
      <Weight>-0.19745952156254071</Weight>
    </ConnectionData>
    <ConnectionData>
      <From>
        <Layer>0</Layer>
        <Node>2</Node>
      </From>
      <To>
        <Layer>1</Layer>
        <Node>16</Node>
      </To>
      <Weight>0.087921659270264962</Weight>
    </ConnectionData>
    <ConnectionData>
      <From>
        <Layer>0</Layer>
        <Node>2</Node>
      </From>
      <To>
        <Layer>1</Layer>
        <Node>17</Node>
      </To>
      <Weight>0.48864362015791407</Weight>
    </ConnectionData>
    <ConnectionData>
      <From>
        <Layer>0</Layer>
        <Node>3</Node>
      </From>
      <To>
        <Layer>1</Layer>
        <Node>0</Node>
      </To>
      <Weight>0.1008710193451825</Weight>
    </ConnectionData>
    <ConnectionData>
      <From>
        <Layer>0</Layer>
        <Node>3</Node>
      </From>
      <To>
        <Layer>1</Layer>
        <Node>1</Node>
      </To>
      <Weight>-0.087818082230080863</Weight>
    </ConnectionData>
    <ConnectionData>
      <From>
        <Layer>0</Layer>
        <Node>3</Node>
      </From>
      <To>
        <Layer>1</Layer>
        <Node>2</Node>
      </To>
      <Weight>0.060459687635516568</Weight>
    </ConnectionData>
    <ConnectionData>
      <From>
        <Layer>0</Layer>
        <Node>3</Node>
      </From>
      <To>
        <Layer>1</Layer>
        <Node>3</Node>
      </To>
      <Weight>0.22759346884097598</Weight>
    </ConnectionData>
    <ConnectionData>
      <From>
        <Layer>0</Layer>
        <Node>3</Node>
      </From>
      <To>
        <Layer>1</Layer>
        <Node>4</Node>
      </To>
      <Weight>-0.46087565643753653</Weight>
    </ConnectionData>
    <ConnectionData>
      <From>
        <Layer>0</Layer>
        <Node>3</Node>
      </From>
      <To>
        <Layer>1</Layer>
        <Node>5</Node>
      </To>
      <Weight>0.14933559468450752</Weight>
    </ConnectionData>
    <ConnectionData>
      <From>
        <Layer>0</Layer>
        <Node>3</Node>
      </From>
      <To>
        <Layer>1</Layer>
        <Node>6</Node>
      </To>
      <Weight>0.21688155351061444</Weight>
    </ConnectionData>
    <ConnectionData>
      <From>
        <Layer>0</Layer>
        <Node>3</Node>
      </From>
      <To>
        <Layer>1</Layer>
        <Node>7</Node>
      </To>
      <Weight>-0.130593268494398</Weight>
    </ConnectionData>
    <ConnectionData>
      <From>
        <Layer>0</Layer>
        <Node>3</Node>
      </From>
      <To>
        <Layer>1</Layer>
        <Node>8</Node>
      </To>
      <Weight>-0.18399929380230573</Weight>
    </ConnectionData>
    <ConnectionData>
      <From>
        <Layer>0</Layer>
        <Node>3</Node>
      </From>
      <To>
        <Layer>1</Layer>
        <Node>9</Node>
      </To>
      <Weight>0.38798906742035832</Weight>
    </ConnectionData>
    <ConnectionData>
      <From>
        <Layer>0</Layer>
        <Node>3</Node>
      </From>
      <To>
        <Layer>1</Layer>
        <Node>10</Node>
      </To>
      <Weight>0.028866783030734755</Weight>
    </ConnectionData>
    <ConnectionData>
      <From>
        <Layer>0</Layer>
        <Node>3</Node>
      </From>
      <To>
        <Layer>1</Layer>
        <Node>11</Node>
      </To>
      <Weight>-0.093214372449188676</Weight>
    </ConnectionData>
    <ConnectionData>
      <From>
        <Layer>0</Layer>
        <Node>3</Node>
      </From>
      <To>
        <Layer>1</Layer>
        <Node>12</Node>
      </To>
      <Weight>0.3792806509320068</Weight>
    </ConnectionData>
    <ConnectionData>
      <From>
        <Layer>0</Layer>
        <Node>3</Node>
      </From>
      <To>
        <Layer>1</Layer>
        <Node>13</Node>
      </To>
      <Weight>0.47316199446709917</Weight>
    </ConnectionData>
    <ConnectionData>
      <From>
        <Layer>0</Layer>
        <Node>3</Node>
      </From>
      <To>
        <Layer>1</Layer>
        <Node>14</Node>
      </To>
      <Weight>-0.45115374119540386</Weight>
    </ConnectionData>
    <ConnectionData>
      <From>
        <Layer>0</Layer>
        <Node>3</Node>
      </From>
      <To>
        <Layer>1</Layer>
        <Node>15</Node>
      </To>
      <Weight>0.40860641603758863</Weight>
    </ConnectionData>
    <ConnectionData>
      <From>
        <Layer>0</Layer>
        <Node>3</Node>
      </From>
      <To>
        <Layer>1</Layer>
        <Node>16</Node>
      </To>
      <Weight>-0.18983532380770674</Weight>
    </ConnectionData>
    <ConnectionData>
      <From>
        <Layer>0</Layer>
        <Node>3</Node>
      </From>
      <To>
        <Layer>1</Layer>
        <Node>17</Node>
      </To>
      <Weight>0.09072738121763213</Weight>
    </ConnectionData>
    <ConnectionData>
      <From>
        <Layer>0</Layer>
        <Node>4</Node>
      </From>
      <To>
        <Layer>1</Layer>
        <Node>0</Node>
      </To>
      <Weight>-0.19193049040247245</Weight>
    </ConnectionData>
    <ConnectionData>
      <From>
        <Layer>0</Layer>
        <Node>4</Node>
      </From>
      <To>
        <Layer>1</Layer>
        <Node>1</Node>
      </To>
      <Weight>0.36250861075823593</Weight>
    </ConnectionData>
    <ConnectionData>
      <From>
        <Layer>0</Layer>
        <Node>4</Node>
      </From>
      <To>
        <Layer>1</Layer>
        <Node>2</Node>
      </To>
      <Weight>0.21145632057984187</Weight>
    </ConnectionData>
    <ConnectionData>
      <From>
        <Layer>0</Layer>
        <Node>4</Node>
      </From>
      <To>
        <Layer>1</Layer>
        <Node>3</Node>
      </To>
      <Weight>0.48025778028194688</Weight>
    </ConnectionData>
    <ConnectionData>
      <From>
        <Layer>0</Layer>
        <Node>4</Node>
      </From>
      <To>
        <Layer>1</Layer>
        <Node>4</Node>
      </To>
      <Weight>0.17288649625744978</Weight>
    </ConnectionData>
    <ConnectionData>
      <From>
        <Layer>0</Layer>
        <Node>4</Node>
      </From>
      <To>
        <Layer>1</Layer>
        <Node>5</Node>
      </To>
      <Weight>0.064587743284454491</Weight>
    </ConnectionData>
    <ConnectionData>
      <From>
        <Layer>0</Layer>
        <Node>4</Node>
      </From>
      <To>
        <Layer>1</Layer>
        <Node>6</Node>
      </To>
      <Weight>0.26559225365779937</Weight>
    </ConnectionData>
    <ConnectionData>
      <From>
        <Layer>0</Layer>
        <Node>4</Node>
      </From>
      <To>
        <Layer>1</Layer>
        <Node>7</Node>
      </To>
      <Weight>-0.20714242509898845</Weight>
    </ConnectionData>
    <ConnectionData>
      <From>
        <Layer>0</Layer>
        <Node>4</Node>
      </From>
      <To>
        <Layer>1</Layer>
        <Node>8</Node>
      </To>
      <Weight>0.10527620446182606</Weight>
    </ConnectionData>
    <ConnectionData>
      <From>
        <Layer>0</Layer>
        <Node>4</Node>
      </From>
      <To>
        <Layer>1</Layer>
        <Node>9</Node>
      </To>
      <Weight>-0.0092482084917129281</Weight>
    </ConnectionData>
    <ConnectionData>
      <From>
        <Layer>0</Layer>
        <Node>4</Node>
      </From>
      <To>
        <Layer>1</Layer>
        <Node>10</Node>
      </To>
      <Weight>0.24797808087802398</Weight>
    </ConnectionData>
    <ConnectionData>
      <From>
        <Layer>0</Layer>
        <Node>4</Node>
      </From>
      <To>
        <Layer>1</Layer>
        <Node>11</Node>
      </To>
      <Weight>-0.32697026935730611</Weight>
    </ConnectionData>
    <ConnectionData>
      <From>
        <Layer>0</Layer>
        <Node>4</Node>
      </From>
      <To>
        <Layer>1</Layer>
        <Node>12</Node>
      </To>
      <Weight>0.22969631279338909</Weight>
    </ConnectionData>
    <ConnectionData>
      <From>
        <Layer>0</Layer>
        <Node>4</Node>
      </From>
      <To>
        <Layer>1</Layer>
        <Node>13</Node>
      </To>
      <Weight>0.464690311795422</Weight>
    </ConnectionData>
    <ConnectionData>
      <From>
        <Layer>0</Layer>
        <Node>4</Node>
      </From>
      <To>
        <Layer>1</Layer>
        <Node>14</Node>
      </To>
      <Weight>0.23120861581117313</Weight>
    </ConnectionData>
    <ConnectionData>
      <From>
        <Layer>0</Layer>
        <Node>4</Node>
      </From>
      <To>
        <Layer>1</Layer>
        <Node>15</Node>
      </To>
      <Weight>-0.41037889007030937</Weight>
    </ConnectionData>
    <ConnectionData>
      <From>
        <Layer>0</Layer>
        <Node>4</Node>
      </From>
      <To>
        <Layer>1</Layer>
        <Node>16</Node>
      </To>
      <Weight>0.13070230029090413</Weight>
    </ConnectionData>
    <ConnectionData>
      <From>
        <Layer>0</Layer>
        <Node>4</Node>
      </From>
      <To>
        <Layer>1</Layer>
        <Node>17</Node>
      </To>
      <Weight>-0.38424315158475336</Weight>
    </ConnectionData>
    <ConnectionData>
      <From>
        <Layer>0</Layer>
        <Node>5</Node>
      </From>
      <To>
        <Layer>1</Layer>
        <Node>0</Node>
      </To>
      <Weight>-0.28163722007611636</Weight>
    </ConnectionData>
    <ConnectionData>
      <From>
        <Layer>0</Layer>
        <Node>5</Node>
      </From>
      <To>
        <Layer>1</Layer>
        <Node>1</Node>
      </To>
      <Weight>-0.4881910439525689</Weight>
    </ConnectionData>
    <ConnectionData>
      <From>
        <Layer>0</Layer>
        <Node>5</Node>
      </From>
      <To>
        <Layer>1</Layer>
        <Node>2</Node>
      </To>
      <Weight>-0.20755482591109109</Weight>
    </ConnectionData>
    <ConnectionData>
      <From>
        <Layer>0</Layer>
        <Node>5</Node>
      </From>
      <To>
        <Layer>1</Layer>
        <Node>3</Node>
      </To>
      <Weight>0.2153609044455741</Weight>
    </ConnectionData>
    <ConnectionData>
      <From>
        <Layer>0</Layer>
        <Node>5</Node>
      </From>
      <To>
        <Layer>1</Layer>
        <Node>4</Node>
      </To>
      <Weight>0.36920187849048614</Weight>
    </ConnectionData>
    <ConnectionData>
      <From>
        <Layer>0</Layer>
        <Node>5</Node>
      </From>
      <To>
        <Layer>1</Layer>
        <Node>5</Node>
      </To>
      <Weight>0.034104019186507961</Weight>
    </ConnectionData>
    <ConnectionData>
      <From>
        <Layer>0</Layer>
        <Node>5</Node>
      </From>
      <To>
        <Layer>1</Layer>
        <Node>6</Node>
      </To>
      <Weight>0.35838730626664461</Weight>
    </ConnectionData>
    <ConnectionData>
      <From>
        <Layer>0</Layer>
        <Node>5</Node>
      </From>
      <To>
        <Layer>1</Layer>
        <Node>7</Node>
      </To>
      <Weight>0.18348858397616474</Weight>
    </ConnectionData>
    <ConnectionData>
      <From>
        <Layer>0</Layer>
        <Node>5</Node>
      </From>
      <To>
        <Layer>1</Layer>
        <Node>8</Node>
      </To>
      <Weight>-0.30989008015482222</Weight>
    </ConnectionData>
    <ConnectionData>
      <From>
        <Layer>0</Layer>
        <Node>5</Node>
      </From>
      <To>
        <Layer>1</Layer>
        <Node>9</Node>
      </To>
      <Weight>0.063863034157018661</Weight>
    </ConnectionData>
    <ConnectionData>
      <From>
        <Layer>0</Layer>
        <Node>5</Node>
      </From>
      <To>
        <Layer>1</Layer>
        <Node>10</Node>
      </To>
      <Weight>0.17840649126023356</Weight>
    </ConnectionData>
    <ConnectionData>
      <From>
        <Layer>0</Layer>
        <Node>5</Node>
      </From>
      <To>
        <Layer>1</Layer>
        <Node>11</Node>
      </To>
      <Weight>-0.39903982630886131</Weight>
    </ConnectionData>
    <ConnectionData>
      <From>
        <Layer>0</Layer>
        <Node>5</Node>
      </From>
      <To>
        <Layer>1</Layer>
        <Node>12</Node>
      </To>
      <Weight>0.34534985238935323</Weight>
    </ConnectionData>
    <ConnectionData>
      <From>
        <Layer>0</Layer>
        <Node>5</Node>
      </From>
      <To>
        <Layer>1</Layer>
        <Node>13</Node>
      </To>
      <Weight>-0.25939214311511821</Weight>
    </ConnectionData>
    <ConnectionData>
      <From>
        <Layer>0</Layer>
        <Node>5</Node>
      </From>
      <To>
        <Layer>1</Layer>
        <Node>14</Node>
      </To>
      <Weight>-0.016844255159070842</Weight>
    </ConnectionData>
    <ConnectionData>
      <From>
        <Layer>0</Layer>
        <Node>5</Node>
      </From>
      <To>
        <Layer>1</Layer>
        <Node>15</Node>
      </To>
      <Weight>-0.38930814708085182</Weight>
    </ConnectionData>
    <ConnectionData>
      <From>
        <Layer>0</Layer>
        <Node>5</Node>
      </From>
      <To>
        <Layer>1</Layer>
        <Node>16</Node>
      </To>
      <Weight>0.4944709688399318</Weight>
    </ConnectionData>
    <ConnectionData>
      <From>
        <Layer>0</Layer>
        <Node>5</Node>
      </From>
      <To>
        <Layer>1</Layer>
        <Node>17</Node>
      </To>
      <Weight>0.22541304851202904</Weight>
    </ConnectionData>
    <ConnectionData>
      <From>
        <Layer>0</Layer>
        <Node>6</Node>
      </From>
      <To>
        <Layer>1</Layer>
        <Node>0</Node>
      </To>
      <Weight>-0.2228127004219278</Weight>
    </ConnectionData>
    <ConnectionData>
      <From>
        <Layer>0</Layer>
        <Node>6</Node>
      </From>
      <To>
        <Layer>1</Layer>
        <Node>1</Node>
      </To>
      <Weight>0.12061323906323562</Weight>
    </ConnectionData>
    <ConnectionData>
      <From>
        <Layer>0</Layer>
        <Node>6</Node>
      </From>
      <To>
        <Layer>1</Layer>
        <Node>2</Node>
      </To>
      <Weight>0.23929542151246941</Weight>
    </ConnectionData>
    <ConnectionData>
      <From>
        <Layer>0</Layer>
        <Node>6</Node>
      </From>
      <To>
        <Layer>1</Layer>
        <Node>3</Node>
      </To>
      <Weight>0.49587194435106219</Weight>
    </ConnectionData>
    <ConnectionData>
      <From>
        <Layer>0</Layer>
        <Node>6</Node>
      </From>
      <To>
        <Layer>1</Layer>
        <Node>4</Node>
      </To>
      <Weight>0.46200121518317672</Weight>
    </ConnectionData>
    <ConnectionData>
      <From>
        <Layer>0</Layer>
        <Node>6</Node>
      </From>
      <To>
        <Layer>1</Layer>
        <Node>5</Node>
      </To>
      <Weight>0.24626676866145192</Weight>
    </ConnectionData>
    <ConnectionData>
      <From>
        <Layer>0</Layer>
        <Node>6</Node>
      </From>
      <To>
        <Layer>1</Layer>
        <Node>6</Node>
      </To>
      <Weight>-0.4559406097773186</Weight>
    </ConnectionData>
    <ConnectionData>
      <From>
        <Layer>0</Layer>
        <Node>6</Node>
      </From>
      <To>
        <Layer>1</Layer>
        <Node>7</Node>
      </To>
      <Weight>-0.27387023799767263</Weight>
    </ConnectionData>
    <ConnectionData>
      <From>
        <Layer>0</Layer>
        <Node>6</Node>
      </From>
      <To>
        <Layer>1</Layer>
        <Node>8</Node>
      </To>
      <Weight>0.12142865062757802</Weight>
    </ConnectionData>
    <ConnectionData>
      <From>
        <Layer>0</Layer>
        <Node>6</Node>
      </From>
      <To>
        <Layer>1</Layer>
        <Node>9</Node>
      </To>
      <Weight>-0.35702902444499962</Weight>
    </ConnectionData>
    <ConnectionData>
      <From>
        <Layer>0</Layer>
        <Node>6</Node>
      </From>
      <To>
        <Layer>1</Layer>
        <Node>10</Node>
      </To>
      <Weight>-0.34170724537303077</Weight>
    </ConnectionData>
    <ConnectionData>
      <From>
        <Layer>0</Layer>
        <Node>6</Node>
      </From>
      <To>
        <Layer>1</Layer>
        <Node>11</Node>
      </To>
      <Weight>0.064176471235312782</Weight>
    </ConnectionData>
    <ConnectionData>
      <From>
        <Layer>0</Layer>
        <Node>6</Node>
      </From>
      <To>
        <Layer>1</Layer>
        <Node>12</Node>
      </To>
      <Weight>0.17557701173963813</Weight>
    </ConnectionData>
    <ConnectionData>
      <From>
        <Layer>0</Layer>
        <Node>6</Node>
      </From>
      <To>
        <Layer>1</Layer>
        <Node>13</Node>
      </To>
      <Weight>0.28965954100231617</Weight>
    </ConnectionData>
    <ConnectionData>
      <From>
        <Layer>0</Layer>
        <Node>6</Node>
      </From>
      <To>
        <Layer>1</Layer>
        <Node>14</Node>
      </To>
      <Weight>-0.15754030582380496</Weight>
    </ConnectionData>
    <ConnectionData>
      <From>
        <Layer>0</Layer>
        <Node>6</Node>
      </From>
      <To>
        <Layer>1</Layer>
        <Node>15</Node>
      </To>
      <Weight>0.43308941038934956</Weight>
    </ConnectionData>
    <ConnectionData>
      <From>
        <Layer>0</Layer>
        <Node>6</Node>
      </From>
      <To>
        <Layer>1</Layer>
        <Node>16</Node>
      </To>
      <Weight>0.19024363611370498</Weight>
    </ConnectionData>
    <ConnectionData>
      <From>
        <Layer>0</Layer>
        <Node>6</Node>
      </From>
      <To>
        <Layer>1</Layer>
        <Node>17</Node>
      </To>
      <Weight>-0.20164427985513783</Weight>
    </ConnectionData>
    <ConnectionData>
      <From>
        <Layer>0</Layer>
        <Node>7</Node>
      </From>
      <To>
        <Layer>1</Layer>
        <Node>0</Node>
      </To>
      <Weight>-0.20171779287127672</Weight>
    </ConnectionData>
    <ConnectionData>
      <From>
        <Layer>0</Layer>
        <Node>7</Node>
      </From>
      <To>
        <Layer>1</Layer>
        <Node>1</Node>
      </To>
      <Weight>0.092708605151953449</Weight>
    </ConnectionData>
    <ConnectionData>
      <From>
        <Layer>0</Layer>
        <Node>7</Node>
      </From>
      <To>
        <Layer>1</Layer>
        <Node>2</Node>
      </To>
      <Weight>0.49330673226774979</Weight>
    </ConnectionData>
    <ConnectionData>
      <From>
        <Layer>0</Layer>
        <Node>7</Node>
      </From>
      <To>
        <Layer>1</Layer>
        <Node>3</Node>
      </To>
      <Weight>-0.32264769860666603</Weight>
    </ConnectionData>
    <ConnectionData>
      <From>
        <Layer>0</Layer>
        <Node>7</Node>
      </From>
      <To>
        <Layer>1</Layer>
        <Node>4</Node>
      </To>
      <Weight>-0.37812952598469773</Weight>
    </ConnectionData>
    <ConnectionData>
      <From>
        <Layer>0</Layer>
        <Node>7</Node>
      </From>
      <To>
        <Layer>1</Layer>
        <Node>5</Node>
      </To>
      <Weight>0.48939791228128504</Weight>
    </ConnectionData>
    <ConnectionData>
      <From>
        <Layer>0</Layer>
        <Node>7</Node>
      </From>
      <To>
        <Layer>1</Layer>
        <Node>6</Node>
      </To>
      <Weight>-0.12552217656072329</Weight>
    </ConnectionData>
    <ConnectionData>
      <From>
        <Layer>0</Layer>
        <Node>7</Node>
      </From>
      <To>
        <Layer>1</Layer>
        <Node>7</Node>
      </To>
      <Weight>-0.29827078049921929</Weight>
    </ConnectionData>
    <ConnectionData>
      <From>
        <Layer>0</Layer>
        <Node>7</Node>
      </From>
      <To>
        <Layer>1</Layer>
        <Node>8</Node>
      </To>
      <Weight>0.11445108364077805</Weight>
    </ConnectionData>
    <ConnectionData>
      <From>
        <Layer>0</Layer>
        <Node>7</Node>
      </From>
      <To>
        <Layer>1</Layer>
        <Node>9</Node>
      </To>
      <Weight>0.004316030770687429</Weight>
    </ConnectionData>
    <ConnectionData>
      <From>
        <Layer>0</Layer>
        <Node>7</Node>
      </From>
      <To>
        <Layer>1</Layer>
        <Node>10</Node>
      </To>
      <Weight>0.14540193911893384</Weight>
    </ConnectionData>
    <ConnectionData>
      <From>
        <Layer>0</Layer>
        <Node>7</Node>
      </From>
      <To>
        <Layer>1</Layer>
        <Node>11</Node>
      </To>
      <Weight>0.0073702239931422442</Weight>
    </ConnectionData>
    <ConnectionData>
      <From>
        <Layer>0</Layer>
        <Node>7</Node>
      </From>
      <To>
        <Layer>1</Layer>
        <Node>12</Node>
      </To>
      <Weight>0.18987398580176473</Weight>
    </ConnectionData>
    <ConnectionData>
      <From>
        <Layer>0</Layer>
        <Node>7</Node>
      </From>
      <To>
        <Layer>1</Layer>
        <Node>13</Node>
      </To>
      <Weight>0.11900445987424091</Weight>
    </ConnectionData>
    <ConnectionData>
      <From>
        <Layer>0</Layer>
        <Node>7</Node>
      </From>
      <To>
        <Layer>1</Layer>
        <Node>14</Node>
      </To>
      <Weight>0.47021934295549028</Weight>
    </ConnectionData>
    <ConnectionData>
      <From>
        <Layer>0</Layer>
        <Node>7</Node>
      </From>
      <To>
        <Layer>1</Layer>
        <Node>15</Node>
      </To>
      <Weight>-0.49420443270085584</Weight>
    </ConnectionData>
    <ConnectionData>
      <From>
        <Layer>0</Layer>
        <Node>7</Node>
      </From>
      <To>
        <Layer>1</Layer>
        <Node>16</Node>
      </To>
      <Weight>0.31243381035161844</Weight>
    </ConnectionData>
    <ConnectionData>
      <From>
        <Layer>0</Layer>
        <Node>7</Node>
      </From>
      <To>
        <Layer>1</Layer>
        <Node>17</Node>
      </To>
      <Weight>-0.48991093877233144</Weight>
    </ConnectionData>
    <ConnectionData>
      <From>
        <Layer>0</Layer>
        <Node>8</Node>
      </From>
      <To>
        <Layer>1</Layer>
        <Node>0</Node>
      </To>
      <Weight>-0.12353857309722277</Weight>
    </ConnectionData>
    <ConnectionData>
      <From>
        <Layer>0</Layer>
        <Node>8</Node>
      </From>
      <To>
        <Layer>1</Layer>
        <Node>1</Node>
      </To>
      <Weight>-0.27750916442717855</Weight>
    </ConnectionData>
    <ConnectionData>
      <From>
        <Layer>0</Layer>
        <Node>8</Node>
      </From>
      <To>
        <Layer>1</Layer>
        <Node>2</Node>
      </To>
      <Weight>-0.45019225913574556</Weight>
    </ConnectionData>
    <ConnectionData>
      <From>
        <Layer>0</Layer>
        <Node>8</Node>
      </From>
      <To>
        <Layer>1</Layer>
        <Node>3</Node>
      </To>
      <Weight>0.046178405427456992</Weight>
    </ConnectionData>
    <ConnectionData>
      <From>
        <Layer>0</Layer>
        <Node>8</Node>
      </From>
      <To>
        <Layer>1</Layer>
        <Node>4</Node>
      </To>
      <Weight>0.17130151422289275</Weight>
    </ConnectionData>
    <ConnectionData>
      <From>
        <Layer>0</Layer>
        <Node>8</Node>
      </From>
      <To>
        <Layer>1</Layer>
        <Node>5</Node>
      </To>
      <Weight>0.14307211648815876</Weight>
    </ConnectionData>
    <ConnectionData>
      <From>
        <Layer>0</Layer>
        <Node>8</Node>
      </From>
      <To>
        <Layer>1</Layer>
        <Node>6</Node>
      </To>
      <Weight>0.41267536855892994</Weight>
    </ConnectionData>
    <ConnectionData>
      <From>
        <Layer>0</Layer>
        <Node>8</Node>
      </From>
      <To>
        <Layer>1</Layer>
        <Node>7</Node>
      </To>
      <Weight>0.21541633071164434</Weight>
    </ConnectionData>
    <ConnectionData>
      <From>
        <Layer>0</Layer>
        <Node>8</Node>
      </From>
      <To>
        <Layer>1</Layer>
        <Node>8</Node>
      </To>
      <Weight>0.025195829349195509</Weight>
    </ConnectionData>
    <ConnectionData>
      <From>
        <Layer>0</Layer>
        <Node>8</Node>
      </From>
      <To>
        <Layer>1</Layer>
        <Node>9</Node>
      </To>
      <Weight>0.125933448609865</Weight>
    </ConnectionData>
    <ConnectionData>
      <From>
        <Layer>0</Layer>
        <Node>8</Node>
      </From>
      <To>
        <Layer>1</Layer>
        <Node>10</Node>
      </To>
      <Weight>0.38828602241738053</Weight>
    </ConnectionData>
    <ConnectionData>
      <From>
        <Layer>0</Layer>
        <Node>8</Node>
      </From>
      <To>
        <Layer>1</Layer>
        <Node>11</Node>
      </To>
      <Weight>0.38874695025791739</Weight>
    </ConnectionData>
    <ConnectionData>
      <From>
        <Layer>0</Layer>
        <Node>8</Node>
      </From>
      <To>
        <Layer>1</Layer>
        <Node>12</Node>
      </To>
      <Weight>0.2585004795149437</Weight>
    </ConnectionData>
    <ConnectionData>
      <From>
        <Layer>0</Layer>
        <Node>8</Node>
      </From>
      <To>
        <Layer>1</Layer>
        <Node>13</Node>
      </To>
      <Weight>0.41226044200000378</Weight>
    </ConnectionData>
    <ConnectionData>
      <From>
        <Layer>0</Layer>
        <Node>8</Node>
      </From>
      <To>
        <Layer>1</Layer>
        <Node>14</Node>
      </To>
      <Weight>0.05036422077117686</Weight>
    </ConnectionData>
    <ConnectionData>
      <From>
        <Layer>0</Layer>
        <Node>8</Node>
      </From>
      <To>
        <Layer>1</Layer>
        <Node>15</Node>
      </To>
      <Weight>-0.315199975303933</Weight>
    </ConnectionData>
    <ConnectionData>
      <From>
        <Layer>0</Layer>
        <Node>8</Node>
      </From>
      <To>
        <Layer>1</Layer>
        <Node>16</Node>
      </To>
      <Weight>0.31240964579042496</Weight>
    </ConnectionData>
    <ConnectionData>
      <From>
        <Layer>0</Layer>
        <Node>8</Node>
      </From>
      <To>
        <Layer>1</Layer>
        <Node>17</Node>
      </To>
      <Weight>-0.0982376363120217</Weight>
    </ConnectionData>
    <ConnectionData>
      <From>
        <Layer>0</Layer>
        <Node>9</Node>
      </From>
      <To>
        <Layer>1</Layer>
        <Node>0</Node>
      </To>
      <Weight>0.23210631624427913</Weight>
    </ConnectionData>
    <ConnectionData>
      <From>
        <Layer>0</Layer>
        <Node>9</Node>
      </From>
      <To>
        <Layer>1</Layer>
        <Node>1</Node>
      </To>
      <Weight>-0.40016500181526177</Weight>
    </ConnectionData>
    <ConnectionData>
      <From>
        <Layer>0</Layer>
        <Node>9</Node>
      </From>
      <To>
        <Layer>1</Layer>
        <Node>2</Node>
      </To>
      <Weight>-0.0012572349520666437</Weight>
    </ConnectionData>
    <ConnectionData>
      <From>
        <Layer>0</Layer>
        <Node>9</Node>
      </From>
      <To>
        <Layer>1</Layer>
        <Node>3</Node>
      </To>
      <Weight>0.24989750923118437</Weight>
    </ConnectionData>
    <ConnectionData>
      <From>
        <Layer>0</Layer>
        <Node>9</Node>
      </From>
      <To>
        <Layer>1</Layer>
        <Node>4</Node>
      </To>
      <Weight>0.12139412091178547</Weight>
    </ConnectionData>
    <ConnectionData>
      <From>
        <Layer>0</Layer>
        <Node>9</Node>
      </From>
      <To>
        <Layer>1</Layer>
        <Node>5</Node>
      </To>
      <Weight>0.260271995682396</Weight>
    </ConnectionData>
    <ConnectionData>
      <From>
        <Layer>0</Layer>
        <Node>9</Node>
      </From>
      <To>
        <Layer>1</Layer>
        <Node>6</Node>
      </To>
      <Weight>-0.36818431497932613</Weight>
    </ConnectionData>
    <ConnectionData>
      <From>
        <Layer>0</Layer>
        <Node>9</Node>
      </From>
      <To>
        <Layer>1</Layer>
        <Node>7</Node>
      </To>
      <Weight>0.039743359451994031</Weight>
    </ConnectionData>
    <ConnectionData>
      <From>
        <Layer>0</Layer>
        <Node>9</Node>
      </From>
      <To>
        <Layer>1</Layer>
        <Node>8</Node>
      </To>
      <Weight>0.08072782288339353</Weight>
    </ConnectionData>
    <ConnectionData>
      <From>
        <Layer>0</Layer>
        <Node>9</Node>
      </From>
      <To>
        <Layer>1</Layer>
        <Node>9</Node>
      </To>
      <Weight>-0.38594157336556423</Weight>
    </ConnectionData>
    <ConnectionData>
      <From>
        <Layer>0</Layer>
        <Node>9</Node>
      </From>
      <To>
        <Layer>1</Layer>
        <Node>10</Node>
      </To>
      <Weight>-0.046903010246764409</Weight>
    </ConnectionData>
    <ConnectionData>
      <From>
        <Layer>0</Layer>
        <Node>9</Node>
      </From>
      <To>
        <Layer>1</Layer>
        <Node>11</Node>
      </To>
      <Weight>0.039288294752728325</Weight>
    </ConnectionData>
    <ConnectionData>
      <From>
        <Layer>0</Layer>
        <Node>9</Node>
      </From>
      <To>
        <Layer>1</Layer>
        <Node>12</Node>
      </To>
      <Weight>0.0939571282798225</Weight>
    </ConnectionData>
    <ConnectionData>
      <From>
        <Layer>0</Layer>
        <Node>9</Node>
      </From>
      <To>
        <Layer>1</Layer>
        <Node>13</Node>
      </To>
      <Weight>0.16978144444049403</Weight>
    </ConnectionData>
    <ConnectionData>
      <From>
        <Layer>0</Layer>
        <Node>9</Node>
      </From>
      <To>
        <Layer>1</Layer>
        <Node>14</Node>
      </To>
      <Weight>0.47722573065069773</Weight>
    </ConnectionData>
    <ConnectionData>
      <From>
        <Layer>0</Layer>
        <Node>9</Node>
      </From>
      <To>
        <Layer>1</Layer>
        <Node>15</Node>
      </To>
      <Weight>-0.16762936705147352</Weight>
    </ConnectionData>
    <ConnectionData>
      <From>
        <Layer>0</Layer>
        <Node>9</Node>
      </From>
      <To>
        <Layer>1</Layer>
        <Node>16</Node>
      </To>
      <Weight>0.056627983486572275</Weight>
    </ConnectionData>
    <ConnectionData>
      <From>
        <Layer>0</Layer>
        <Node>9</Node>
      </From>
      <To>
        <Layer>1</Layer>
        <Node>17</Node>
      </To>
      <Weight>-0.032247199459116527</Weight>
    </ConnectionData>
    <ConnectionData>
      <From>
        <Layer>0</Layer>
        <Node>10</Node>
      </From>
      <To>
        <Layer>1</Layer>
        <Node>0</Node>
      </To>
      <Weight>-0.25145202071939221</Weight>
    </ConnectionData>
    <ConnectionData>
      <From>
        <Layer>0</Layer>
        <Node>10</Node>
      </From>
      <To>
        <Layer>1</Layer>
        <Node>1</Node>
      </To>
      <Weight>0.25210380170126623</Weight>
    </ConnectionData>
    <ConnectionData>
      <From>
        <Layer>0</Layer>
        <Node>10</Node>
      </From>
      <To>
        <Layer>1</Layer>
        <Node>2</Node>
      </To>
      <Weight>0.4214070909290607</Weight>
    </ConnectionData>
    <ConnectionData>
      <From>
        <Layer>0</Layer>
        <Node>10</Node>
      </From>
      <To>
        <Layer>1</Layer>
        <Node>3</Node>
      </To>
      <Weight>-0.14976538422040891</Weight>
    </ConnectionData>
    <ConnectionData>
      <From>
        <Layer>0</Layer>
        <Node>10</Node>
      </From>
      <To>
        <Layer>1</Layer>
        <Node>4</Node>
      </To>
      <Weight>-0.23532306716559598</Weight>
    </ConnectionData>
    <ConnectionData>
      <From>
        <Layer>0</Layer>
        <Node>10</Node>
      </From>
      <To>
        <Layer>1</Layer>
        <Node>5</Node>
      </To>
      <Weight>-0.093545856696342078</Weight>
    </ConnectionData>
    <ConnectionData>
      <From>
        <Layer>0</Layer>
        <Node>10</Node>
      </From>
      <To>
        <Layer>1</Layer>
        <Node>6</Node>
      </To>
      <Weight>-0.035797917067910523</Weight>
    </ConnectionData>
    <ConnectionData>
      <From>
        <Layer>0</Layer>
        <Node>10</Node>
      </From>
      <To>
        <Layer>1</Layer>
        <Node>7</Node>
      </To>
      <Weight>0.24854437482941172</Weight>
    </ConnectionData>
    <ConnectionData>
      <From>
        <Layer>0</Layer>
        <Node>10</Node>
      </From>
      <To>
        <Layer>1</Layer>
        <Node>8</Node>
      </To>
      <Weight>-0.18655680291659982</Weight>
    </ConnectionData>
    <ConnectionData>
      <From>
        <Layer>0</Layer>
        <Node>10</Node>
      </From>
      <To>
        <Layer>1</Layer>
        <Node>9</Node>
      </To>
      <Weight>0.22570413338286066</Weight>
    </ConnectionData>
    <ConnectionData>
      <From>
        <Layer>0</Layer>
        <Node>10</Node>
      </From>
      <To>
        <Layer>1</Layer>
        <Node>10</Node>
      </To>
      <Weight>0.24581555125574373</Weight>
    </ConnectionData>
    <ConnectionData>
      <From>
        <Layer>0</Layer>
        <Node>10</Node>
      </From>
      <To>
        <Layer>1</Layer>
        <Node>11</Node>
      </To>
      <Weight>0.23314149711893006</Weight>
    </ConnectionData>
    <ConnectionData>
      <From>
        <Layer>0</Layer>
        <Node>10</Node>
      </From>
      <To>
        <Layer>1</Layer>
        <Node>12</Node>
      </To>
      <Weight>0.45700600322196538</Weight>
    </ConnectionData>
    <ConnectionData>
      <From>
        <Layer>0</Layer>
        <Node>10</Node>
      </From>
      <To>
        <Layer>1</Layer>
        <Node>13</Node>
      </To>
      <Weight>0.0050739611056978</Weight>
    </ConnectionData>
    <ConnectionData>
      <From>
        <Layer>0</Layer>
        <Node>10</Node>
      </From>
      <To>
        <Layer>1</Layer>
        <Node>14</Node>
      </To>
      <Weight>0.30659481408381595</Weight>
    </ConnectionData>
    <ConnectionData>
      <From>
        <Layer>0</Layer>
        <Node>10</Node>
      </From>
      <To>
        <Layer>1</Layer>
        <Node>15</Node>
      </To>
      <Weight>0.06845697926751193</Weight>
    </ConnectionData>
    <ConnectionData>
      <From>
        <Layer>0</Layer>
        <Node>10</Node>
      </From>
      <To>
        <Layer>1</Layer>
        <Node>16</Node>
      </To>
      <Weight>-0.22631074894513503</Weight>
    </ConnectionData>
    <ConnectionData>
      <From>
        <Layer>0</Layer>
        <Node>10</Node>
      </From>
      <To>
        <Layer>1</Layer>
        <Node>17</Node>
      </To>
      <Weight>0.21259881216688026</Weight>
    </ConnectionData>
    <ConnectionData>
      <From>
        <Layer>0</Layer>
        <Node>11</Node>
      </From>
      <To>
        <Layer>1</Layer>
        <Node>0</Node>
      </To>
      <Weight>0.01134629617973526</Weight>
    </ConnectionData>
    <ConnectionData>
      <From>
        <Layer>0</Layer>
        <Node>11</Node>
      </From>
      <To>
        <Layer>1</Layer>
        <Node>1</Node>
      </To>
      <Weight>0.12656391767159292</Weight>
    </ConnectionData>
    <ConnectionData>
      <From>
        <Layer>0</Layer>
        <Node>11</Node>
      </From>
      <To>
        <Layer>1</Layer>
        <Node>2</Node>
      </To>
      <Weight>0.10109671466103598</Weight>
    </ConnectionData>
    <ConnectionData>
      <From>
        <Layer>0</Layer>
        <Node>11</Node>
      </From>
      <To>
        <Layer>1</Layer>
        <Node>3</Node>
      </To>
      <Weight>-0.21046425481814157</Weight>
    </ConnectionData>
    <ConnectionData>
      <From>
        <Layer>0</Layer>
        <Node>11</Node>
      </From>
      <To>
        <Layer>1</Layer>
        <Node>4</Node>
      </To>
      <Weight>-0.085637279593216875</Weight>
    </ConnectionData>
    <ConnectionData>
      <From>
        <Layer>0</Layer>
        <Node>11</Node>
      </From>
      <To>
        <Layer>1</Layer>
        <Node>5</Node>
      </To>
      <Weight>-0.36844184522910128</Weight>
    </ConnectionData>
    <ConnectionData>
      <From>
        <Layer>0</Layer>
        <Node>11</Node>
      </From>
      <To>
        <Layer>1</Layer>
        <Node>6</Node>
      </To>
      <Weight>-0.43765570639523477</Weight>
    </ConnectionData>
    <ConnectionData>
      <From>
        <Layer>0</Layer>
        <Node>11</Node>
      </From>
      <To>
        <Layer>1</Layer>
        <Node>7</Node>
      </To>
      <Weight>0.29861694192449417</Weight>
    </ConnectionData>
    <ConnectionData>
      <From>
        <Layer>0</Layer>
        <Node>11</Node>
      </From>
      <To>
        <Layer>1</Layer>
        <Node>8</Node>
      </To>
      <Weight>-0.2376806590415913</Weight>
    </ConnectionData>
    <ConnectionData>
      <From>
        <Layer>0</Layer>
        <Node>11</Node>
      </From>
      <To>
        <Layer>1</Layer>
        <Node>9</Node>
      </To>
      <Weight>0.48590753459646718</Weight>
    </ConnectionData>
    <ConnectionData>
      <From>
        <Layer>0</Layer>
        <Node>11</Node>
      </From>
      <To>
        <Layer>1</Layer>
        <Node>10</Node>
      </To>
      <Weight>-0.46802367966995745</Weight>
    </ConnectionData>
    <ConnectionData>
      <From>
        <Layer>0</Layer>
        <Node>11</Node>
      </From>
      <To>
        <Layer>1</Layer>
        <Node>11</Node>
      </To>
      <Weight>-0.28149542202311356</Weight>
    </ConnectionData>
    <ConnectionData>
      <From>
        <Layer>0</Layer>
        <Node>11</Node>
      </From>
      <To>
        <Layer>1</Layer>
        <Node>12</Node>
      </To>
      <Weight>0.41152121960721966</Weight>
    </ConnectionData>
    <ConnectionData>
      <From>
        <Layer>0</Layer>
        <Node>11</Node>
      </From>
      <To>
        <Layer>1</Layer>
        <Node>13</Node>
      </To>
      <Weight>-0.07387015343358283</Weight>
    </ConnectionData>
    <ConnectionData>
      <From>
        <Layer>0</Layer>
        <Node>11</Node>
      </From>
      <To>
        <Layer>1</Layer>
        <Node>14</Node>
      </To>
      <Weight>-0.14436754148656855</Weight>
    </ConnectionData>
    <ConnectionData>
      <From>
        <Layer>0</Layer>
        <Node>11</Node>
      </From>
      <To>
        <Layer>1</Layer>
        <Node>15</Node>
      </To>
      <Weight>-0.41738857976970661</Weight>
    </ConnectionData>
    <ConnectionData>
      <From>
        <Layer>0</Layer>
        <Node>11</Node>
      </From>
      <To>
        <Layer>1</Layer>
        <Node>16</Node>
      </To>
      <Weight>0.43625204541545926</Weight>
    </ConnectionData>
    <ConnectionData>
      <From>
        <Layer>0</Layer>
        <Node>11</Node>
      </From>
      <To>
        <Layer>1</Layer>
        <Node>17</Node>
      </To>
      <Weight>-0.43969415591084127</Weight>
    </ConnectionData>
    <ConnectionData>
      <From>
        <Layer>0</Layer>
        <Node>12</Node>
      </From>
      <To>
        <Layer>1</Layer>
        <Node>0</Node>
      </To>
      <Weight>-0.01964472724108246</Weight>
    </ConnectionData>
    <ConnectionData>
      <From>
        <Layer>0</Layer>
        <Node>12</Node>
      </From>
      <To>
        <Layer>1</Layer>
        <Node>1</Node>
      </To>
      <Weight>-0.1181282995353119</Weight>
    </ConnectionData>
    <ConnectionData>
      <From>
        <Layer>0</Layer>
        <Node>12</Node>
      </From>
      <To>
        <Layer>1</Layer>
        <Node>2</Node>
      </To>
      <Weight>0.33515806535033421</Weight>
    </ConnectionData>
    <ConnectionData>
      <From>
        <Layer>0</Layer>
        <Node>12</Node>
      </From>
      <To>
        <Layer>1</Layer>
        <Node>3</Node>
      </To>
      <Weight>-0.40771137825572462</Weight>
    </ConnectionData>
    <ConnectionData>
      <From>
        <Layer>0</Layer>
        <Node>12</Node>
      </From>
      <To>
        <Layer>1</Layer>
        <Node>4</Node>
      </To>
      <Weight>-0.21430457370090511</Weight>
    </ConnectionData>
    <ConnectionData>
      <From>
        <Layer>0</Layer>
        <Node>12</Node>
      </From>
      <To>
        <Layer>1</Layer>
        <Node>5</Node>
      </To>
      <Weight>0.37284974608237376</Weight>
    </ConnectionData>
    <ConnectionData>
      <From>
        <Layer>0</Layer>
        <Node>12</Node>
      </From>
      <To>
        <Layer>1</Layer>
        <Node>6</Node>
      </To>
      <Weight>-0.053171201401004176</Weight>
    </ConnectionData>
    <ConnectionData>
      <From>
        <Layer>0</Layer>
        <Node>12</Node>
      </From>
      <To>
        <Layer>1</Layer>
        <Node>7</Node>
      </To>
      <Weight>-0.093888448362186738</Weight>
    </ConnectionData>
    <ConnectionData>
      <From>
        <Layer>0</Layer>
        <Node>12</Node>
      </From>
      <To>
        <Layer>1</Layer>
        <Node>8</Node>
      </To>
      <Weight>0.29392780819625031</Weight>
    </ConnectionData>
    <ConnectionData>
      <From>
        <Layer>0</Layer>
        <Node>12</Node>
      </From>
      <To>
        <Layer>1</Layer>
        <Node>9</Node>
      </To>
      <Weight>0.34758632576446347</Weight>
    </ConnectionData>
    <ConnectionData>
      <From>
        <Layer>0</Layer>
        <Node>12</Node>
      </From>
      <To>
        <Layer>1</Layer>
        <Node>10</Node>
      </To>
      <Weight>-0.34294757658752967</Weight>
    </ConnectionData>
    <ConnectionData>
      <From>
        <Layer>0</Layer>
        <Node>12</Node>
      </From>
      <To>
        <Layer>1</Layer>
        <Node>11</Node>
      </To>
      <Weight>0.44802302864753785</Weight>
    </ConnectionData>
    <ConnectionData>
      <From>
        <Layer>0</Layer>
        <Node>12</Node>
      </From>
      <To>
        <Layer>1</Layer>
        <Node>12</Node>
      </To>
      <Weight>0.23269348066891238</Weight>
    </ConnectionData>
    <ConnectionData>
      <From>
        <Layer>0</Layer>
        <Node>12</Node>
      </From>
      <To>
        <Layer>1</Layer>
        <Node>13</Node>
      </To>
      <Weight>-0.47449985098768949</Weight>
    </ConnectionData>
    <ConnectionData>
      <From>
        <Layer>0</Layer>
        <Node>12</Node>
      </From>
      <To>
        <Layer>1</Layer>
        <Node>14</Node>
      </To>
      <Weight>-0.10390780661437093</Weight>
    </ConnectionData>
    <ConnectionData>
      <From>
        <Layer>0</Layer>
        <Node>12</Node>
      </From>
      <To>
        <Layer>1</Layer>
        <Node>15</Node>
      </To>
      <Weight>-0.23537308151618258</Weight>
    </ConnectionData>
    <ConnectionData>
      <From>
        <Layer>0</Layer>
        <Node>12</Node>
      </From>
      <To>
        <Layer>1</Layer>
        <Node>16</Node>
      </To>
      <Weight>0.32102433676879127</Weight>
    </ConnectionData>
    <ConnectionData>
      <From>
        <Layer>0</Layer>
        <Node>12</Node>
      </From>
      <To>
        <Layer>1</Layer>
        <Node>17</Node>
      </To>
      <Weight>0.43006406581497936</Weight>
    </ConnectionData>
    <ConnectionData>
      <From>
        <Layer>0</Layer>
        <Node>13</Node>
      </From>
      <To>
        <Layer>1</Layer>
        <Node>0</Node>
      </To>
      <Weight>0.36665608587984744</Weight>
    </ConnectionData>
    <ConnectionData>
      <From>
        <Layer>0</Layer>
        <Node>13</Node>
      </From>
      <To>
        <Layer>1</Layer>
        <Node>1</Node>
      </To>
      <Weight>0.45901223409874936</Weight>
    </ConnectionData>
    <ConnectionData>
      <From>
        <Layer>0</Layer>
        <Node>13</Node>
      </From>
      <To>
        <Layer>1</Layer>
        <Node>2</Node>
      </To>
      <Weight>-0.1622589187055169</Weight>
    </ConnectionData>
    <ConnectionData>
      <From>
        <Layer>0</Layer>
        <Node>13</Node>
      </From>
      <To>
        <Layer>1</Layer>
        <Node>3</Node>
      </To>
      <Weight>0.2898489361581621</Weight>
    </ConnectionData>
    <ConnectionData>
      <From>
        <Layer>0</Layer>
        <Node>13</Node>
      </From>
      <To>
        <Layer>1</Layer>
        <Node>4</Node>
      </To>
      <Weight>-0.21210967782517415</Weight>
    </ConnectionData>
    <ConnectionData>
      <From>
        <Layer>0</Layer>
        <Node>13</Node>
      </From>
      <To>
        <Layer>1</Layer>
        <Node>5</Node>
      </To>
      <Weight>-0.033940009090090151</Weight>
    </ConnectionData>
    <ConnectionData>
      <From>
        <Layer>0</Layer>
        <Node>13</Node>
      </From>
      <To>
        <Layer>1</Layer>
        <Node>6</Node>
      </To>
      <Weight>-0.35586519765475078</Weight>
    </ConnectionData>
    <ConnectionData>
      <From>
        <Layer>0</Layer>
        <Node>13</Node>
      </From>
      <To>
        <Layer>1</Layer>
        <Node>7</Node>
      </To>
      <Weight>-0.021705451664377706</Weight>
    </ConnectionData>
    <ConnectionData>
      <From>
        <Layer>0</Layer>
        <Node>13</Node>
      </From>
      <To>
        <Layer>1</Layer>
        <Node>8</Node>
      </To>
      <Weight>0.21656805449936911</Weight>
    </ConnectionData>
    <ConnectionData>
      <From>
        <Layer>0</Layer>
        <Node>13</Node>
      </From>
      <To>
        <Layer>1</Layer>
        <Node>9</Node>
      </To>
      <Weight>-0.40506138089348626</Weight>
    </ConnectionData>
    <ConnectionData>
      <From>
        <Layer>0</Layer>
        <Node>13</Node>
      </From>
      <To>
        <Layer>1</Layer>
        <Node>10</Node>
      </To>
      <Weight>0.314182913775641</Weight>
    </ConnectionData>
    <ConnectionData>
      <From>
        <Layer>0</Layer>
        <Node>13</Node>
      </From>
      <To>
        <Layer>1</Layer>
        <Node>11</Node>
      </To>
      <Weight>-0.18031429531067344</Weight>
    </ConnectionData>
    <ConnectionData>
      <From>
        <Layer>0</Layer>
        <Node>13</Node>
      </From>
      <To>
        <Layer>1</Layer>
        <Node>12</Node>
      </To>
      <Weight>-0.12249096139450139</Weight>
    </ConnectionData>
    <ConnectionData>
      <From>
        <Layer>0</Layer>
        <Node>13</Node>
      </From>
      <To>
        <Layer>1</Layer>
        <Node>13</Node>
      </To>
      <Weight>0.37439458299167205</Weight>
    </ConnectionData>
    <ConnectionData>
      <From>
        <Layer>0</Layer>
        <Node>13</Node>
      </From>
      <To>
        <Layer>1</Layer>
        <Node>14</Node>
      </To>
      <Weight>0.068821915690238544</Weight>
    </ConnectionData>
    <ConnectionData>
      <From>
        <Layer>0</Layer>
        <Node>13</Node>
      </From>
      <To>
        <Layer>1</Layer>
        <Node>15</Node>
      </To>
      <Weight>0.24628896999465721</Weight>
    </ConnectionData>
    <ConnectionData>
      <From>
        <Layer>0</Layer>
        <Node>13</Node>
      </From>
      <To>
        <Layer>1</Layer>
        <Node>16</Node>
      </To>
      <Weight>-0.41189829349140555</Weight>
    </ConnectionData>
    <ConnectionData>
      <From>
        <Layer>0</Layer>
        <Node>13</Node>
      </From>
      <To>
        <Layer>1</Layer>
        <Node>17</Node>
      </To>
      <Weight>0.39181755059017687</Weight>
    </ConnectionData>
    <ConnectionData>
      <From>
        <Layer>0</Layer>
        <Node>14</Node>
      </From>
      <To>
        <Layer>1</Layer>
        <Node>0</Node>
      </To>
      <Weight>0.37744074681654605</Weight>
    </ConnectionData>
    <ConnectionData>
      <From>
        <Layer>0</Layer>
        <Node>14</Node>
      </From>
      <To>
        <Layer>1</Layer>
        <Node>1</Node>
      </To>
      <Weight>-0.080942325564540119</Weight>
    </ConnectionData>
    <ConnectionData>
      <From>
        <Layer>0</Layer>
        <Node>14</Node>
      </From>
      <To>
        <Layer>1</Layer>
        <Node>2</Node>
      </To>
      <Weight>-0.15913150862750203</Weight>
    </ConnectionData>
    <ConnectionData>
      <From>
        <Layer>0</Layer>
        <Node>14</Node>
      </From>
      <To>
        <Layer>1</Layer>
        <Node>3</Node>
      </To>
      <Weight>0.22824696857866222</Weight>
    </ConnectionData>
    <ConnectionData>
      <From>
        <Layer>0</Layer>
        <Node>14</Node>
      </From>
      <To>
        <Layer>1</Layer>
        <Node>4</Node>
      </To>
      <Weight>0.3427069465828626</Weight>
    </ConnectionData>
    <ConnectionData>
      <From>
        <Layer>0</Layer>
        <Node>14</Node>
      </From>
      <To>
        <Layer>1</Layer>
        <Node>5</Node>
      </To>
      <Weight>-0.49174883123103008</Weight>
    </ConnectionData>
    <ConnectionData>
      <From>
        <Layer>0</Layer>
        <Node>14</Node>
      </From>
      <To>
        <Layer>1</Layer>
        <Node>6</Node>
      </To>
      <Weight>-0.16236965342535153</Weight>
    </ConnectionData>
    <ConnectionData>
      <From>
        <Layer>0</Layer>
        <Node>14</Node>
      </From>
      <To>
        <Layer>1</Layer>
        <Node>7</Node>
      </To>
      <Weight>-0.28524203215969823</Weight>
    </ConnectionData>
    <ConnectionData>
      <From>
        <Layer>0</Layer>
        <Node>14</Node>
      </From>
      <To>
        <Layer>1</Layer>
        <Node>8</Node>
      </To>
      <Weight>0.1415645185120239</Weight>
    </ConnectionData>
    <ConnectionData>
      <From>
        <Layer>0</Layer>
        <Node>14</Node>
      </From>
      <To>
        <Layer>1</Layer>
        <Node>9</Node>
      </To>
      <Weight>-0.18570368768912909</Weight>
    </ConnectionData>
    <ConnectionData>
      <From>
        <Layer>0</Layer>
        <Node>14</Node>
      </From>
      <To>
        <Layer>1</Layer>
        <Node>10</Node>
      </To>
      <Weight>-0.24678594607244525</Weight>
    </ConnectionData>
    <ConnectionData>
      <From>
        <Layer>0</Layer>
        <Node>14</Node>
      </From>
      <To>
        <Layer>1</Layer>
        <Node>11</Node>
      </To>
      <Weight>-0.49352382868226796</Weight>
    </ConnectionData>
    <ConnectionData>
      <From>
        <Layer>0</Layer>
        <Node>14</Node>
      </From>
      <To>
        <Layer>1</Layer>
        <Node>12</Node>
      </To>
      <Weight>0.32241238459125743</Weight>
    </ConnectionData>
    <ConnectionData>
      <From>
        <Layer>0</Layer>
        <Node>14</Node>
      </From>
      <To>
        <Layer>1</Layer>
        <Node>13</Node>
      </To>
      <Weight>0.14689430112340218</Weight>
    </ConnectionData>
    <ConnectionData>
      <From>
        <Layer>0</Layer>
        <Node>14</Node>
      </From>
      <To>
        <Layer>1</Layer>
        <Node>14</Node>
      </To>
      <Weight>0.1051055097976259</Weight>
    </ConnectionData>
    <ConnectionData>
      <From>
        <Layer>0</Layer>
        <Node>14</Node>
      </From>
      <To>
        <Layer>1</Layer>
        <Node>15</Node>
      </To>
      <Weight>-0.074431607301547964</Weight>
    </ConnectionData>
    <ConnectionData>
      <From>
        <Layer>0</Layer>
        <Node>14</Node>
      </From>
      <To>
        <Layer>1</Layer>
        <Node>16</Node>
      </To>
      <Weight>-0.28404466564955411</Weight>
    </ConnectionData>
    <ConnectionData>
      <From>
        <Layer>0</Layer>
        <Node>14</Node>
      </From>
      <To>
        <Layer>1</Layer>
        <Node>17</Node>
      </To>
      <Weight>0.47723981131670989</Weight>
    </ConnectionData>
    <ConnectionData>
      <From>
        <Layer>0</Layer>
        <Node>15</Node>
      </From>
      <To>
        <Layer>1</Layer>
        <Node>0</Node>
      </To>
      <Weight>0.22256476279467563</Weight>
    </ConnectionData>
    <ConnectionData>
      <From>
        <Layer>0</Layer>
        <Node>15</Node>
      </From>
      <To>
        <Layer>1</Layer>
        <Node>1</Node>
      </To>
      <Weight>0.19050633660075544</Weight>
    </ConnectionData>
    <ConnectionData>
      <From>
        <Layer>0</Layer>
        <Node>15</Node>
      </From>
      <To>
        <Layer>1</Layer>
        <Node>2</Node>
      </To>
      <Weight>-0.40601862171013775</Weight>
    </ConnectionData>
    <ConnectionData>
      <From>
        <Layer>0</Layer>
        <Node>15</Node>
      </From>
      <To>
        <Layer>1</Layer>
        <Node>3</Node>
      </To>
      <Weight>-0.13090192555957564</Weight>
    </ConnectionData>
    <ConnectionData>
      <From>
        <Layer>0</Layer>
        <Node>15</Node>
      </From>
      <To>
        <Layer>1</Layer>
        <Node>4</Node>
      </To>
      <Weight>0.4481538193990261</Weight>
    </ConnectionData>
    <ConnectionData>
      <From>
        <Layer>0</Layer>
        <Node>15</Node>
      </From>
      <To>
        <Layer>1</Layer>
        <Node>5</Node>
      </To>
      <Weight>0.3074008779634726</Weight>
    </ConnectionData>
    <ConnectionData>
      <From>
        <Layer>0</Layer>
        <Node>15</Node>
      </From>
      <To>
        <Layer>1</Layer>
        <Node>6</Node>
      </To>
      <Weight>-0.34371830841699536</Weight>
    </ConnectionData>
    <ConnectionData>
      <From>
        <Layer>0</Layer>
        <Node>15</Node>
      </From>
      <To>
        <Layer>1</Layer>
        <Node>7</Node>
      </To>
      <Weight>-0.14810982050751792</Weight>
    </ConnectionData>
    <ConnectionData>
      <From>
        <Layer>0</Layer>
        <Node>15</Node>
      </From>
      <To>
        <Layer>1</Layer>
        <Node>8</Node>
      </To>
      <Weight>0.091928637862172313</Weight>
    </ConnectionData>
    <ConnectionData>
      <From>
        <Layer>0</Layer>
        <Node>15</Node>
      </From>
      <To>
        <Layer>1</Layer>
        <Node>9</Node>
      </To>
      <Weight>-0.025757896493076304</Weight>
    </ConnectionData>
    <ConnectionData>
      <From>
        <Layer>0</Layer>
        <Node>15</Node>
      </From>
      <To>
        <Layer>1</Layer>
        <Node>10</Node>
      </To>
      <Weight>-0.029922712841035204</Weight>
    </ConnectionData>
    <ConnectionData>
      <From>
        <Layer>0</Layer>
        <Node>15</Node>
      </From>
      <To>
        <Layer>1</Layer>
        <Node>11</Node>
      </To>
      <Weight>-0.21734215957920167</Weight>
    </ConnectionData>
    <ConnectionData>
      <From>
        <Layer>0</Layer>
        <Node>15</Node>
      </From>
      <To>
        <Layer>1</Layer>
        <Node>12</Node>
      </To>
      <Weight>-0.12079888704270075</Weight>
    </ConnectionData>
    <ConnectionData>
      <From>
        <Layer>0</Layer>
        <Node>15</Node>
      </From>
      <To>
        <Layer>1</Layer>
        <Node>13</Node>
      </To>
      <Weight>0.48640451067425516</Weight>
    </ConnectionData>
    <ConnectionData>
      <From>
        <Layer>0</Layer>
        <Node>15</Node>
      </From>
      <To>
        <Layer>1</Layer>
        <Node>14</Node>
      </To>
      <Weight>0.43739844250371607</Weight>
    </ConnectionData>
    <ConnectionData>
      <From>
        <Layer>0</Layer>
        <Node>15</Node>
      </From>
      <To>
        <Layer>1</Layer>
        <Node>15</Node>
      </To>
      <Weight>0.0042746427954521993</Weight>
    </ConnectionData>
    <ConnectionData>
      <From>
        <Layer>0</Layer>
        <Node>15</Node>
      </From>
      <To>
        <Layer>1</Layer>
        <Node>16</Node>
      </To>
      <Weight>-0.11281382833272863</Weight>
    </ConnectionData>
    <ConnectionData>
      <From>
        <Layer>0</Layer>
        <Node>15</Node>
      </From>
      <To>
        <Layer>1</Layer>
        <Node>17</Node>
      </To>
      <Weight>-0.098033337666668607</Weight>
    </ConnectionData>
    <ConnectionData>
      <From>
        <Layer>0</Layer>
        <Node>16</Node>
      </From>
      <To>
        <Layer>1</Layer>
        <Node>0</Node>
      </To>
      <Weight>0.089195574442481385</Weight>
    </ConnectionData>
    <ConnectionData>
      <From>
        <Layer>0</Layer>
        <Node>16</Node>
      </From>
      <To>
        <Layer>1</Layer>
        <Node>1</Node>
      </To>
      <Weight>-0.36159088269881479</Weight>
    </ConnectionData>
    <ConnectionData>
      <From>
        <Layer>0</Layer>
        <Node>16</Node>
      </From>
      <To>
        <Layer>1</Layer>
        <Node>2</Node>
      </To>
      <Weight>-0.38369471248411324</Weight>
    </ConnectionData>
    <ConnectionData>
      <From>
        <Layer>0</Layer>
        <Node>16</Node>
      </From>
      <To>
        <Layer>1</Layer>
        <Node>3</Node>
      </To>
      <Weight>-0.17051008747448682</Weight>
    </ConnectionData>
    <ConnectionData>
      <From>
        <Layer>0</Layer>
        <Node>16</Node>
      </From>
      <To>
        <Layer>1</Layer>
        <Node>4</Node>
      </To>
      <Weight>-0.047781410416486425</Weight>
    </ConnectionData>
    <ConnectionData>
      <From>
        <Layer>0</Layer>
        <Node>16</Node>
      </From>
      <To>
        <Layer>1</Layer>
        <Node>5</Node>
      </To>
      <Weight>-0.42686764566547591</Weight>
    </ConnectionData>
    <ConnectionData>
      <From>
        <Layer>0</Layer>
        <Node>16</Node>
      </From>
      <To>
        <Layer>1</Layer>
        <Node>6</Node>
      </To>
      <Weight>0.324495472397886</Weight>
    </ConnectionData>
    <ConnectionData>
      <From>
        <Layer>0</Layer>
        <Node>16</Node>
      </From>
      <To>
        <Layer>1</Layer>
        <Node>7</Node>
      </To>
      <Weight>0.32983849003437837</Weight>
    </ConnectionData>
    <ConnectionData>
      <From>
        <Layer>0</Layer>
        <Node>16</Node>
      </From>
      <To>
        <Layer>1</Layer>
        <Node>8</Node>
      </To>
      <Weight>-0.27491950559193246</Weight>
    </ConnectionData>
    <ConnectionData>
      <From>
        <Layer>0</Layer>
        <Node>16</Node>
      </From>
      <To>
        <Layer>1</Layer>
        <Node>9</Node>
      </To>
      <Weight>0.21009188318163707</Weight>
    </ConnectionData>
    <ConnectionData>
      <From>
        <Layer>0</Layer>
        <Node>16</Node>
      </From>
      <To>
        <Layer>1</Layer>
        <Node>10</Node>
      </To>
      <Weight>-0.22747376548474363</Weight>
    </ConnectionData>
    <ConnectionData>
      <From>
        <Layer>0</Layer>
        <Node>16</Node>
      </From>
      <To>
        <Layer>1</Layer>
        <Node>11</Node>
      </To>
      <Weight>-0.33271138734776129</Weight>
    </ConnectionData>
    <ConnectionData>
      <From>
        <Layer>0</Layer>
        <Node>16</Node>
      </From>
      <To>
        <Layer>1</Layer>
        <Node>12</Node>
      </To>
      <Weight>0.21458019489170066</Weight>
    </ConnectionData>
    <ConnectionData>
      <From>
        <Layer>0</Layer>
        <Node>16</Node>
      </From>
      <To>
        <Layer>1</Layer>
        <Node>13</Node>
      </To>
      <Weight>0.45194064590704652</Weight>
    </ConnectionData>
    <ConnectionData>
      <From>
        <Layer>0</Layer>
        <Node>16</Node>
      </From>
      <To>
        <Layer>1</Layer>
        <Node>14</Node>
      </To>
      <Weight>0.15843924864122605</Weight>
    </ConnectionData>
    <ConnectionData>
      <From>
        <Layer>0</Layer>
        <Node>16</Node>
      </From>
      <To>
        <Layer>1</Layer>
        <Node>15</Node>
      </To>
      <Weight>0.09158210437352865</Weight>
    </ConnectionData>
    <ConnectionData>
      <From>
        <Layer>0</Layer>
        <Node>16</Node>
      </From>
      <To>
        <Layer>1</Layer>
        <Node>16</Node>
      </To>
      <Weight>-0.47627579280001847</Weight>
    </ConnectionData>
    <ConnectionData>
      <From>
        <Layer>0</Layer>
        <Node>16</Node>
      </From>
      <To>
        <Layer>1</Layer>
        <Node>17</Node>
      </To>
      <Weight>-0.10240463009216105</Weight>
    </ConnectionData>
    <ConnectionData>
      <From>
        <Layer>0</Layer>
        <Node>17</Node>
      </From>
      <To>
        <Layer>1</Layer>
        <Node>0</Node>
      </To>
      <Weight>0.29783617230031456</Weight>
    </ConnectionData>
    <ConnectionData>
      <From>
        <Layer>0</Layer>
        <Node>17</Node>
      </From>
      <To>
        <Layer>1</Layer>
        <Node>1</Node>
      </To>
      <Weight>0.00834267237612174</Weight>
    </ConnectionData>
    <ConnectionData>
      <From>
        <Layer>0</Layer>
        <Node>17</Node>
      </From>
      <To>
        <Layer>1</Layer>
        <Node>2</Node>
      </To>
      <Weight>-0.029096144963566273</Weight>
    </ConnectionData>
    <ConnectionData>
      <From>
        <Layer>0</Layer>
        <Node>17</Node>
      </From>
      <To>
        <Layer>1</Layer>
        <Node>3</Node>
      </To>
      <Weight>0.033467613409025376</Weight>
    </ConnectionData>
    <ConnectionData>
      <From>
        <Layer>0</Layer>
        <Node>17</Node>
      </From>
      <To>
        <Layer>1</Layer>
        <Node>4</Node>
      </To>
      <Weight>0.071965276995657579</Weight>
    </ConnectionData>
    <ConnectionData>
      <From>
        <Layer>0</Layer>
        <Node>17</Node>
      </From>
      <To>
        <Layer>1</Layer>
        <Node>5</Node>
      </To>
      <Weight>-0.0091832329096194765</Weight>
    </ConnectionData>
    <ConnectionData>
      <From>
        <Layer>0</Layer>
        <Node>17</Node>
      </From>
      <To>
        <Layer>1</Layer>
        <Node>6</Node>
      </To>
      <Weight>-0.083677469093202339</Weight>
    </ConnectionData>
    <ConnectionData>
      <From>
        <Layer>0</Layer>
        <Node>17</Node>
      </From>
      <To>
        <Layer>1</Layer>
        <Node>7</Node>
      </To>
      <Weight>0.36338824306772477</Weight>
    </ConnectionData>
    <ConnectionData>
      <From>
        <Layer>0</Layer>
        <Node>17</Node>
      </From>
      <To>
        <Layer>1</Layer>
        <Node>8</Node>
      </To>
      <Weight>0.24468068068133697</Weight>
    </ConnectionData>
    <ConnectionData>
      <From>
        <Layer>0</Layer>
        <Node>17</Node>
      </From>
      <To>
        <Layer>1</Layer>
        <Node>9</Node>
      </To>
      <Weight>-0.14109332190877449</Weight>
    </ConnectionData>
    <ConnectionData>
      <From>
        <Layer>0</Layer>
        <Node>17</Node>
      </From>
      <To>
        <Layer>1</Layer>
        <Node>10</Node>
      </To>
      <Weight>0.43509519935357166</Weight>
    </ConnectionData>
    <ConnectionData>
      <From>
        <Layer>0</Layer>
        <Node>17</Node>
      </From>
      <To>
        <Layer>1</Layer>
        <Node>11</Node>
      </To>
      <Weight>-0.23319045674670041</Weight>
    </ConnectionData>
    <ConnectionData>
      <From>
        <Layer>0</Layer>
        <Node>17</Node>
      </From>
      <To>
        <Layer>1</Layer>
        <Node>12</Node>
      </To>
      <Weight>-0.43092227118598403</Weight>
    </ConnectionData>
    <ConnectionData>
      <From>
        <Layer>0</Layer>
        <Node>17</Node>
      </From>
      <To>
        <Layer>1</Layer>
        <Node>13</Node>
      </To>
      <Weight>-0.18186225820419483</Weight>
    </ConnectionData>
    <ConnectionData>
      <From>
        <Layer>0</Layer>
        <Node>17</Node>
      </From>
      <To>
        <Layer>1</Layer>
        <Node>14</Node>
      </To>
      <Weight>-0.24029187054386913</Weight>
    </ConnectionData>
    <ConnectionData>
      <From>
        <Layer>0</Layer>
        <Node>17</Node>
      </From>
      <To>
        <Layer>1</Layer>
        <Node>15</Node>
      </To>
      <Weight>-0.29686115253570544</Weight>
    </ConnectionData>
    <ConnectionData>
      <From>
        <Layer>0</Layer>
        <Node>17</Node>
      </From>
      <To>
        <Layer>1</Layer>
        <Node>16</Node>
      </To>
      <Weight>0.33637281825597065</Weight>
    </ConnectionData>
    <ConnectionData>
      <From>
        <Layer>0</Layer>
        <Node>17</Node>
      </From>
      <To>
        <Layer>1</Layer>
        <Node>17</Node>
      </To>
      <Weight>-0.42245378295073927</Weight>
    </ConnectionData>
    <ConnectionData>
      <From>
        <Layer>1</Layer>
        <Node>0</Node>
      </From>
      <To>
        <Layer>2</Layer>
        <Node>0</Node>
      </To>
      <Weight>0.36093452380082314</Weight>
    </ConnectionData>
    <ConnectionData>
      <From>
        <Layer>1</Layer>
        <Node>0</Node>
      </From>
      <To>
        <Layer>2</Layer>
        <Node>1</Node>
      </To>
      <Weight>-0.1069251497308375</Weight>
    </ConnectionData>
    <ConnectionData>
      <From>
        <Layer>1</Layer>
        <Node>0</Node>
      </From>
      <To>
        <Layer>2</Layer>
        <Node>2</Node>
      </To>
      <Weight>-0.26171225298275813</Weight>
    </ConnectionData>
    <ConnectionData>
      <From>
        <Layer>1</Layer>
        <Node>0</Node>
      </From>
      <To>
        <Layer>2</Layer>
        <Node>3</Node>
      </To>
      <Weight>-0.47915097604466184</Weight>
    </ConnectionData>
    <ConnectionData>
      <From>
        <Layer>1</Layer>
        <Node>1</Node>
      </From>
      <To>
        <Layer>2</Layer>
        <Node>0</Node>
      </To>
      <Weight>0.044602602042538408</Weight>
    </ConnectionData>
    <ConnectionData>
      <From>
        <Layer>1</Layer>
        <Node>1</Node>
      </From>
      <To>
        <Layer>2</Layer>
        <Node>1</Node>
      </To>
      <Weight>-0.38168467063535222</Weight>
    </ConnectionData>
    <ConnectionData>
      <From>
        <Layer>1</Layer>
        <Node>1</Node>
      </From>
      <To>
        <Layer>2</Layer>
        <Node>2</Node>
      </To>
      <Weight>0.082320383555405052</Weight>
    </ConnectionData>
    <ConnectionData>
      <From>
        <Layer>1</Layer>
        <Node>1</Node>
      </From>
      <To>
        <Layer>2</Layer>
        <Node>3</Node>
      </To>
      <Weight>-0.053810191598632484</Weight>
    </ConnectionData>
    <ConnectionData>
      <From>
        <Layer>1</Layer>
        <Node>2</Node>
      </From>
      <To>
        <Layer>2</Layer>
        <Node>0</Node>
      </To>
      <Weight>-0.42063605502277429</Weight>
    </ConnectionData>
    <ConnectionData>
      <From>
        <Layer>1</Layer>
        <Node>2</Node>
      </From>
      <To>
        <Layer>2</Layer>
        <Node>1</Node>
      </To>
      <Weight>-0.075359974790066453</Weight>
    </ConnectionData>
    <ConnectionData>
      <From>
        <Layer>1</Layer>
        <Node>2</Node>
      </From>
      <To>
        <Layer>2</Layer>
        <Node>2</Node>
      </To>
      <Weight>0.25966190861522309</Weight>
    </ConnectionData>
    <ConnectionData>
      <From>
        <Layer>1</Layer>
        <Node>2</Node>
      </From>
      <To>
        <Layer>2</Layer>
        <Node>3</Node>
      </To>
      <Weight>0.018136641251918273</Weight>
    </ConnectionData>
    <ConnectionData>
      <From>
        <Layer>1</Layer>
        <Node>3</Node>
      </From>
      <To>
        <Layer>2</Layer>
        <Node>0</Node>
      </To>
      <Weight>0.12421859177957228</Weight>
    </ConnectionData>
    <ConnectionData>
      <From>
        <Layer>1</Layer>
        <Node>3</Node>
      </From>
      <To>
        <Layer>2</Layer>
        <Node>1</Node>
      </To>
      <Weight>0.28761900858377065</Weight>
    </ConnectionData>
    <ConnectionData>
      <From>
        <Layer>1</Layer>
        <Node>3</Node>
      </From>
      <To>
        <Layer>2</Layer>
        <Node>2</Node>
      </To>
      <Weight>0.46268030347427369</Weight>
    </ConnectionData>
    <ConnectionData>
      <From>
        <Layer>1</Layer>
        <Node>3</Node>
      </From>
      <To>
        <Layer>2</Layer>
        <Node>3</Node>
      </To>
      <Weight>0.03980307259587712</Weight>
    </ConnectionData>
    <ConnectionData>
      <From>
        <Layer>1</Layer>
        <Node>4</Node>
      </From>
      <To>
        <Layer>2</Layer>
        <Node>0</Node>
      </To>
      <Weight>0.20643847049513764</Weight>
    </ConnectionData>
    <ConnectionData>
      <From>
        <Layer>1</Layer>
        <Node>4</Node>
      </From>
      <To>
        <Layer>2</Layer>
        <Node>1</Node>
      </To>
      <Weight>0.37884349929114969</Weight>
    </ConnectionData>
    <ConnectionData>
      <From>
        <Layer>1</Layer>
        <Node>4</Node>
      </From>
      <To>
        <Layer>2</Layer>
        <Node>2</Node>
      </To>
      <Weight>0.43106280729689761</Weight>
    </ConnectionData>
    <ConnectionData>
      <From>
        <Layer>1</Layer>
        <Node>4</Node>
      </From>
      <To>
        <Layer>2</Layer>
        <Node>3</Node>
      </To>
      <Weight>-0.444272038966544</Weight>
    </ConnectionData>
    <ConnectionData>
      <From>
        <Layer>1</Layer>
        <Node>5</Node>
      </From>
      <To>
        <Layer>2</Layer>
        <Node>0</Node>
      </To>
      <Weight>0.066443840305527635</Weight>
    </ConnectionData>
    <ConnectionData>
      <From>
        <Layer>1</Layer>
        <Node>5</Node>
      </From>
      <To>
        <Layer>2</Layer>
        <Node>1</Node>
      </To>
      <Weight>0.12548852042550618</Weight>
    </ConnectionData>
    <ConnectionData>
      <From>
        <Layer>1</Layer>
        <Node>5</Node>
      </From>
      <To>
        <Layer>2</Layer>
        <Node>2</Node>
      </To>
      <Weight>0.41316738161871558</Weight>
    </ConnectionData>
    <ConnectionData>
      <From>
        <Layer>1</Layer>
        <Node>5</Node>
      </From>
      <To>
        <Layer>2</Layer>
        <Node>3</Node>
      </To>
      <Weight>0.0888303465157888</Weight>
    </ConnectionData>
    <ConnectionData>
      <From>
        <Layer>1</Layer>
        <Node>6</Node>
      </From>
      <To>
        <Layer>2</Layer>
        <Node>0</Node>
      </To>
      <Weight>-0.17154832634681294</Weight>
    </ConnectionData>
    <ConnectionData>
      <From>
        <Layer>1</Layer>
        <Node>6</Node>
      </From>
      <To>
        <Layer>2</Layer>
        <Node>1</Node>
      </To>
      <Weight>-0.034411205693339553</Weight>
    </ConnectionData>
    <ConnectionData>
      <From>
        <Layer>1</Layer>
        <Node>6</Node>
      </From>
      <To>
        <Layer>2</Layer>
        <Node>2</Node>
      </To>
      <Weight>0.39474329068080671</Weight>
    </ConnectionData>
    <ConnectionData>
      <From>
        <Layer>1</Layer>
        <Node>6</Node>
      </From>
      <To>
        <Layer>2</Layer>
        <Node>3</Node>
      </To>
      <Weight>0.458270951154768</Weight>
    </ConnectionData>
    <ConnectionData>
      <From>
        <Layer>1</Layer>
        <Node>7</Node>
      </From>
      <To>
        <Layer>2</Layer>
        <Node>0</Node>
      </To>
      <Weight>0.1410141543676211</Weight>
    </ConnectionData>
    <ConnectionData>
      <From>
        <Layer>1</Layer>
        <Node>7</Node>
      </From>
      <To>
        <Layer>2</Layer>
        <Node>1</Node>
      </To>
      <Weight>0.45438849271945114</Weight>
    </ConnectionData>
    <ConnectionData>
      <From>
        <Layer>1</Layer>
        <Node>7</Node>
      </From>
      <To>
        <Layer>2</Layer>
        <Node>2</Node>
      </To>
      <Weight>0.40758048319610785</Weight>
    </ConnectionData>
    <ConnectionData>
      <From>
        <Layer>1</Layer>
        <Node>7</Node>
      </From>
      <To>
        <Layer>2</Layer>
        <Node>3</Node>
      </To>
      <Weight>0.01144134742740599</Weight>
    </ConnectionData>
    <ConnectionData>
      <From>
        <Layer>1</Layer>
        <Node>8</Node>
      </From>
      <To>
        <Layer>2</Layer>
        <Node>0</Node>
      </To>
      <Weight>-0.38443217234892407</Weight>
    </ConnectionData>
    <ConnectionData>
      <From>
        <Layer>1</Layer>
        <Node>8</Node>
      </From>
      <To>
        <Layer>2</Layer>
        <Node>1</Node>
      </To>
      <Weight>0.08089303159196537</Weight>
    </ConnectionData>
    <ConnectionData>
      <From>
        <Layer>1</Layer>
        <Node>8</Node>
      </From>
      <To>
        <Layer>2</Layer>
        <Node>2</Node>
      </To>
      <Weight>0.23064758057270551</Weight>
    </ConnectionData>
    <ConnectionData>
      <From>
        <Layer>1</Layer>
        <Node>8</Node>
      </From>
      <To>
        <Layer>2</Layer>
        <Node>3</Node>
      </To>
      <Weight>0.13064935693081903</Weight>
    </ConnectionData>
    <ConnectionData>
      <From>
        <Layer>1</Layer>
        <Node>9</Node>
      </From>
      <To>
        <Layer>2</Layer>
        <Node>0</Node>
      </To>
      <Weight>-0.340692377109403</Weight>
    </ConnectionData>
    <ConnectionData>
      <From>
        <Layer>1</Layer>
        <Node>9</Node>
      </From>
      <To>
        <Layer>2</Layer>
        <Node>1</Node>
      </To>
      <Weight>0.2769871483449764</Weight>
    </ConnectionData>
    <ConnectionData>
      <From>
        <Layer>1</Layer>
        <Node>9</Node>
      </From>
      <To>
        <Layer>2</Layer>
        <Node>2</Node>
      </To>
      <Weight>0.46374007033358333</Weight>
    </ConnectionData>
    <ConnectionData>
      <From>
        <Layer>1</Layer>
        <Node>9</Node>
      </From>
      <To>
        <Layer>2</Layer>
        <Node>3</Node>
      </To>
      <Weight>-0.14741147432821405</Weight>
    </ConnectionData>
    <ConnectionData>
      <From>
        <Layer>1</Layer>
        <Node>10</Node>
      </From>
      <To>
        <Layer>2</Layer>
        <Node>0</Node>
      </To>
      <Weight>0.45114722985362044</Weight>
    </ConnectionData>
    <ConnectionData>
      <From>
        <Layer>1</Layer>
        <Node>10</Node>
      </From>
      <To>
        <Layer>2</Layer>
        <Node>1</Node>
      </To>
      <Weight>-0.37422453140570994</Weight>
    </ConnectionData>
    <ConnectionData>
      <From>
        <Layer>1</Layer>
        <Node>10</Node>
      </From>
      <To>
        <Layer>2</Layer>
        <Node>2</Node>
      </To>
      <Weight>-0.088547177886845185</Weight>
    </ConnectionData>
    <ConnectionData>
      <From>
        <Layer>1</Layer>
        <Node>10</Node>
      </From>
      <To>
        <Layer>2</Layer>
        <Node>3</Node>
      </To>
      <Weight>0.49168250569686411</Weight>
    </ConnectionData>
    <ConnectionData>
      <From>
        <Layer>1</Layer>
        <Node>11</Node>
      </From>
      <To>
        <Layer>2</Layer>
        <Node>0</Node>
      </To>
      <Weight>-0.39627366554749832</Weight>
    </ConnectionData>
    <ConnectionData>
      <From>
        <Layer>1</Layer>
        <Node>11</Node>
      </From>
      <To>
        <Layer>2</Layer>
        <Node>1</Node>
      </To>
      <Weight>-0.27345596057058125</Weight>
    </ConnectionData>
    <ConnectionData>
      <From>
        <Layer>1</Layer>
        <Node>11</Node>
      </From>
      <To>
        <Layer>2</Layer>
        <Node>2</Node>
      </To>
      <Weight>0.23468808631165328</Weight>
    </ConnectionData>
    <ConnectionData>
      <From>
        <Layer>1</Layer>
        <Node>11</Node>
      </From>
      <To>
        <Layer>2</Layer>
        <Node>3</Node>
      </To>
      <Weight>-0.352523809230199</Weight>
    </ConnectionData>
    <ConnectionData>
      <From>
        <Layer>1</Layer>
        <Node>12</Node>
      </From>
      <To>
        <Layer>2</Layer>
        <Node>0</Node>
      </To>
      <Weight>-0.1958707602209741</Weight>
    </ConnectionData>
    <ConnectionData>
      <From>
        <Layer>1</Layer>
        <Node>12</Node>
      </From>
      <To>
        <Layer>2</Layer>
        <Node>1</Node>
      </To>
      <Weight>0.02927465621813885</Weight>
    </ConnectionData>
    <ConnectionData>
      <From>
        <Layer>1</Layer>
        <Node>12</Node>
      </From>
      <To>
        <Layer>2</Layer>
        <Node>2</Node>
      </To>
      <Weight>0.11169927130066759</Weight>
    </ConnectionData>
    <ConnectionData>
      <From>
        <Layer>1</Layer>
        <Node>12</Node>
      </From>
      <To>
        <Layer>2</Layer>
        <Node>3</Node>
      </To>
      <Weight>-0.11913536983501882</Weight>
    </ConnectionData>
    <ConnectionData>
      <From>
        <Layer>1</Layer>
        <Node>13</Node>
      </From>
      <To>
        <Layer>2</Layer>
        <Node>0</Node>
      </To>
      <Weight>-0.22792395983260311</Weight>
    </ConnectionData>
    <ConnectionData>
      <From>
        <Layer>1</Layer>
        <Node>13</Node>
      </From>
      <To>
        <Layer>2</Layer>
        <Node>1</Node>
      </To>
      <Weight>0.28064485722251464</Weight>
    </ConnectionData>
    <ConnectionData>
      <From>
        <Layer>1</Layer>
        <Node>13</Node>
      </From>
      <To>
        <Layer>2</Layer>
        <Node>2</Node>
      </To>
      <Weight>0.011102376743733156</Weight>
    </ConnectionData>
    <ConnectionData>
      <From>
        <Layer>1</Layer>
        <Node>13</Node>
      </From>
      <To>
        <Layer>2</Layer>
        <Node>3</Node>
      </To>
      <Weight>-0.26455399662468304</Weight>
    </ConnectionData>
    <ConnectionData>
      <From>
        <Layer>1</Layer>
        <Node>14</Node>
      </From>
      <To>
        <Layer>2</Layer>
        <Node>0</Node>
      </To>
      <Weight>-0.020092531349553022</Weight>
    </ConnectionData>
    <ConnectionData>
      <From>
        <Layer>1</Layer>
        <Node>14</Node>
      </From>
      <To>
        <Layer>2</Layer>
        <Node>1</Node>
      </To>
      <Weight>0.14945740050145306</Weight>
    </ConnectionData>
    <ConnectionData>
      <From>
        <Layer>1</Layer>
        <Node>14</Node>
      </From>
      <To>
        <Layer>2</Layer>
        <Node>2</Node>
      </To>
      <Weight>0.1923973503021511</Weight>
    </ConnectionData>
    <ConnectionData>
      <From>
        <Layer>1</Layer>
        <Node>14</Node>
      </From>
      <To>
        <Layer>2</Layer>
        <Node>3</Node>
      </To>
      <Weight>-0.42098619226412204</Weight>
    </ConnectionData>
    <ConnectionData>
      <From>
        <Layer>1</Layer>
        <Node>15</Node>
      </From>
      <To>
        <Layer>2</Layer>
        <Node>0</Node>
      </To>
      <Weight>-0.276427961316159</Weight>
    </ConnectionData>
    <ConnectionData>
      <From>
        <Layer>1</Layer>
        <Node>15</Node>
      </From>
      <To>
        <Layer>2</Layer>
        <Node>1</Node>
      </To>
      <Weight>0.12404943240063704</Weight>
    </ConnectionData>
    <ConnectionData>
      <From>
        <Layer>1</Layer>
        <Node>15</Node>
      </From>
      <To>
        <Layer>2</Layer>
        <Node>2</Node>
      </To>
      <Weight>0.30517565403374636</Weight>
    </ConnectionData>
    <ConnectionData>
      <From>
        <Layer>1</Layer>
        <Node>15</Node>
      </From>
      <To>
        <Layer>2</Layer>
        <Node>3</Node>
      </To>
      <Weight>-0.37502454774222549</Weight>
    </ConnectionData>
    <ConnectionData>
      <From>
        <Layer>1</Layer>
        <Node>16</Node>
      </From>
      <To>
        <Layer>2</Layer>
        <Node>0</Node>
      </To>
      <Weight>0.017059542013825646</Weight>
    </ConnectionData>
    <ConnectionData>
      <From>
        <Layer>1</Layer>
        <Node>16</Node>
      </From>
      <To>
        <Layer>2</Layer>
        <Node>1</Node>
      </To>
      <Weight>-0.25177943881218295</Weight>
    </ConnectionData>
    <ConnectionData>
      <From>
        <Layer>1</Layer>
        <Node>16</Node>
      </From>
      <To>
        <Layer>2</Layer>
        <Node>2</Node>
      </To>
      <Weight>-0.09743118639915771</Weight>
    </ConnectionData>
    <ConnectionData>
      <From>
        <Layer>1</Layer>
        <Node>16</Node>
      </From>
      <To>
        <Layer>2</Layer>
        <Node>3</Node>
      </To>
      <Weight>-0.45667443981239314</Weight>
    </ConnectionData>
    <ConnectionData>
      <From>
        <Layer>1</Layer>
        <Node>17</Node>
      </From>
      <To>
        <Layer>2</Layer>
        <Node>0</Node>
      </To>
      <Weight>-0.44302857198893492</Weight>
    </ConnectionData>
    <ConnectionData>
      <From>
        <Layer>1</Layer>
        <Node>17</Node>
      </From>
      <To>
        <Layer>2</Layer>
        <Node>1</Node>
      </To>
      <Weight>-0.16796905345654539</Weight>
    </ConnectionData>
    <ConnectionData>
      <From>
        <Layer>1</Layer>
        <Node>17</Node>
      </From>
      <To>
        <Layer>2</Layer>
        <Node>2</Node>
      </To>
      <Weight>-0.1195045502947199</Weight>
    </ConnectionData>
    <ConnectionData>
      <From>
        <Layer>1</Layer>
        <Node>17</Node>
      </From>
      <To>
        <Layer>2</Layer>
        <Node>3</Node>
      </To>
      <Weight>0.42945132215016113</Weight>
    </ConnectionData>
  </Connections>
  <InputLayerId>0</InputLayerId>
  <OutputLayerId>2</OutputLayerId>
</NetworkData>